{
  "id": "isaiah-48-tabbed",
  "title": "Isaiah Chapter 48 Quiz - Multi-Level",
  "description": "An enhanced quiz on Isaiah chapter 48 with Easy, Medium, Hard, and Theological levels. Each level has 15 carefully crafted questions. Choose your difficulty and dive in!",
  "tabs": {
    "easy": {
      "id": "isaiah-48-easy",
      "title": "Isaiah Chapter 48 Quiz - Easy Level",
      "description": "Perfect for beginners! Test your basic knowledge of Isaiah Chapter 48.",
      "type": "chapter",
      "book": "Isaiah",
      "chapter": 48,
      "questions": [
        {
          "id": "isaiah-48-easy-q1",
          "question": "According to Isaiah 48:1, who is called by the name of Israel?",
          "type": "multiple-choice",
          "options": [
            "The house of Jacob",
            "The house of David",
            "The house of Judah",
            "The house of Egypt"
          ],
          "correctAnswer": "The house of Jacob",
          "explanation": "Isaiah 48:1 states that the house of Jacob are called by the name of Israel.",
          "verseReference": "Isaiah 48:1",
          "difficulty": "easy"
        },
        {
          "id": "isaiah-48-easy-q2",
          "question": "In Isaiah 48:3, what does God say about the former things?",
          "type": "multiple-choice",
          "options": [
            "He declared them from the beginning",
            "He forgot them",
            "He kept them secret",
            "He changed them often"
          ],
          "correctAnswer": "He declared them from the beginning",
          "explanation": "Isaiah 48:3 says God declared the former things from the beginning and showed them.",
          "verseReference": "Isaiah 48:3",
          "difficulty": "easy"
        },
        {
          "id": "isaiah-48-easy-q3",
          "question": "What does Isaiah 48:4 say about the neck and brow of the people?",
          "type": "multiple-choice",
          "options": [
            "Neck is an iron sinew and brow is brass",
            "Neck is soft and brow is gold",
            "Neck is weak and brow is silver",
            "Neck is clay and brow is wood"
          ],
          "correctAnswer": "Neck is an iron sinew and brow is brass",
          "explanation": "Isaiah 48:4 describes the neck as an iron sinew and the brow as brass, indicating obstinacy.",
          "verseReference": "Isaiah 48:4",
          "difficulty": "easy"
        },
        {
          "id": "isaiah-48-easy-q4",
          "question": "Why did God declare things before they came to pass according to Isaiah 48:5?",
          "type": "multiple-choice",
          "options": [
            "So that people would not say their idols did them",
            "To confuse the people",
            "To bring fear to the nations",
            "To reward the righteous"
          ],
          "correctAnswer": "So that people would not say their idols did them",
          "explanation": "Isaiah 48:5 states God declared things beforehand so people would not claim their idols caused them.",
          "verseReference": "Isaiah 48:5",
          "difficulty": "easy"
        },
        {
          "id": "isaiah-48-easy-q5",
          "question": "According to Isaiah 48:9, why does God defer His anger?",
          "type": "multiple-choice",
          "options": [
            "For His name's sake",
            "Because He is weak",
            "To please the people",
            "Because He forgot"
          ],
          "correctAnswer": "For His name's sake",
          "explanation": "Isaiah 48:9 says God defers His anger for His name's sake and to refrain from cutting them off.",
          "verseReference": "Isaiah 48:9",
          "difficulty": "easy"
        },
        {
          "id": "isaiah-48-easy-q6",
          "question": "What does God say He has refined the people with in Isaiah 48:10?",
          "type": "multiple-choice",
          "options": [
            "The furnace of affliction",
            "Silver",
            "Gold",
            "Water"
          ],
          "correctAnswer": "The furnace of affliction",
          "explanation": "Isaiah 48:10 explains God refined the people in the furnace of affliction, not with silver.",
          "verseReference": "Isaiah 48:10",
          "difficulty": "easy"
        },
        {
          "id": "isaiah-48-easy-q7",
          "question": "In Isaiah 48:12, how does God describe Himself?",
          "type": "multiple-choice",
          "options": [
            "I am the first and the last",
            "I am a prophet",
            "I am a king",
            "I am a stranger"
          ],
          "correctAnswer": "I am the first and the last",
          "explanation": "Isaiah 48:12 says God is the first and the last, emphasizing His eternal nature.",
          "verseReference": "Isaiah 48:12",
          "difficulty": "easy"
        },
        {
          "id": "isaiah-48-easy-q8",
          "question": "What did God's hand lay according to Isaiah 48:13?",
          "type": "multiple-choice",
          "options": [
            "The foundation of the earth",
            "The foundation of the temple",
            "The foundation of the city",
            "The foundation of the heavens"
          ],
          "correctAnswer": "The foundation of the earth",
          "explanation": "Isaiah 48:13 states God's hand laid the foundation of the earth and His right hand spanned the heavens.",
          "verseReference": "Isaiah 48:13",
          "difficulty": "easy"
        },
        {
          "id": "isaiah-48-easy-q9",
          "question": "Who will God do His pleasure on as mentioned in Isaiah 48:14?",
          "type": "multiple-choice",
          "options": [
            "Babylon",
            "Egypt",
            "Assyria",
            "Philistines"
          ],
          "correctAnswer": "Babylon",
          "explanation": "Isaiah 48:14 says God will do His pleasure on Babylon and His arm will be on the Chaldeans.",
          "verseReference": "Isaiah 48:14",
          "difficulty": "easy"
        },
        {
          "id": "isaiah-48-easy-q10",
          "question": "According to Isaiah 48:17, who is the Redeemer and Holy One of Israel?",
          "type": "multiple-choice",
          "options": [
            "The LORD thy God",
            "Moses",
            "David",
            "Elijah"
          ],
          "correctAnswer": "The LORD thy God",
          "explanation": "Isaiah 48:17 identifies the Redeemer and Holy One of Israel as the LORD thy God.",
          "verseReference": "Isaiah 48:17",
          "difficulty": "easy"
        },
        {
          "id": "isaiah-48-easy-q11",
          "question": "True or False: Isaiah 48:22 states that there is peace to the wicked.",
          "type": "true-false",
          "options": [
            "True",
            "False"
          ],
          "correctAnswer": "False",
          "explanation": "Isaiah 48:22 clearly states there is no peace to the wicked.",
          "verseReference": "Isaiah 48:22",
          "difficulty": "easy"
        },
        {
          "id": "isaiah-48-easy-q12",
          "question": "True or False: Isaiah 48:21 mentions that God caused waters to flow out of the rock for His people.",
          "type": "true-false",
          "options": [
            "True",
            "False"
          ],
          "correctAnswer": "True",
          "explanation": "Isaiah 48:21 says God caused waters to flow out of the rock when He led His people through the deserts.",
          "verseReference": "Isaiah 48:21",
          "difficulty": "easy"
        },
        {
          "id": "isaiah-48-easy-q13",
          "question": "True or False: Isaiah 48:6 says God only showed old things and no new things.",
          "type": "true-false",
          "options": [
            "True",
            "False"
          ],
          "correctAnswer": "False",
          "explanation": "Isaiah 48:6 states God showed new things and hidden things that were not previously known.",
          "verseReference": "Isaiah 48:6",
          "difficulty": "easy"
        },
        {
          "id": "isaiah-48-easy-q14",
          "question": "Complete this verse from Isaiah 48:18: 'O that thou hadst hearkened to my commandments! then had thy peace been as a ______, and thy righteousness as the waves of the sea:'",
          "type": "fill-blank",
          "options": [
            "river",
            "mountain",
            "tree",
            "cloud"
          ],
          "correctAnswer": "river",
          "explanation": "Isaiah 48:18 compares peace to a river if the commandments were hearkened to.",
          "verseReference": "Isaiah 48:18",
          "difficulty": "easy"
        },
        {
          "id": "isaiah-48-easy-q15",
          "question": "Complete this verse from Isaiah 48:20: 'Go ye forth of Babylon, flee ye from the Chaldeans, with a voice of singing declare ye, tell this, utter it even to the end of the earth; say ye, The LORD hath ______ his servant Jacob.'",
          "type": "fill-blank",
          "options": [
            "redeemed",
            "destroyed",
            "forgotten",
            "judged"
          ],
          "correctAnswer": "redeemed",
          "explanation": "Isaiah 48:20 commands to declare that the LORD hath redeemed His servant Jacob.",
          "verseReference": "Isaiah 48:20",
          "difficulty": "easy"
        }
      ],
      "difficulty": "easy",
      "isBookQuiz": false,
      "slug": "isaiah-48-quiz",
      "tags": [
        "isaiah",
        "chapter-48",
        "isaiah",
        "bible-quiz",
        "easy"
      ],
      "totalQuestions": 15,
      "estimatedTime": 8
    },
    "medium": {
      "id": "isaiah-48-medium",
      "title": "Isaiah Chapter 48 Quiz - Medium Level",
      "description": "Ready for more? Apply biblical truths from Isaiah Chapter 48 to real-life situations.",
      "type": "chapter",
      "book": "Isaiah",
      "chapter": 48,
      "questions": [
        {
          "id": "isaiah-48-medium-q1",
          "question": "A fellow believer is struggling with trusting God's plan during difficult times. Based on Isaiah 48, what biblical truth would you share about God's purpose in affliction?",
          "type": "multiple-choice",
          "options": [
            "God refines His people through affliction to purify them",
            "Affliction means God has abandoned you",
            "Suffering is punishment without purpose",
            "God only uses blessings, not trials, for growth"
          ],
          "correctAnswer": "God refines His people through affliction to purify them",
          "explanation": "Isaiah 48:10 says God has refined His people in the furnace of affliction, teaching that hardships serve to purify and strengthen faith. This is supported by verses 9, 11, and 17 which emphasize God's purpose and care.",
          "verseReference": "Isaiah 48:10",
          "difficulty": "medium"
        },
        {
          "id": "isaiah-48-medium-q2",
          "question": "How does Isaiah 48 teach us about the importance of obedience to God's commandments for experiencing peace?",
          "type": "multiple-choice",
          "options": [
            "Obedience brings peace like a flowing river",
            "Peace comes only through wealth",
            "Commandments are optional for peace",
            "Peace is unrelated to righteousness"
          ],
          "correctAnswer": "Obedience brings peace like a flowing river",
          "explanation": "Isaiah 48:18 highlights that hearkening to God's commandments results in peace like a river and righteousness like waves of the sea, showing the blessing of obedience.",
          "verseReference": "Isaiah 48:18",
          "difficulty": "medium"
        },
        {
          "id": "isaiah-48-medium-q3",
          "question": "A believer wonders how God reveals His plans and assures His people. What does Isaiah 48 say about God's declaration of future events?",
          "type": "multiple-choice",
          "options": [
            "God declares things from the beginning so people know He is God",
            "God hides his plans until they happen",
            "Prophets guess God's plans without certainty",
            "People must rely on idols for guidance"
          ],
          "correctAnswer": "God declares things from the beginning so people know He is God",
          "explanation": "Isaiah 48:3-5 explains God declared former things from the beginning and showed them so people would not attribute His works to idols, confirming His sovereignty.",
          "verseReference": "Isaiah 48:3",
          "difficulty": "medium"
        },
        {
          "id": "isaiah-48-medium-q4",
          "question": "How does this chapter teach about God's faithfulness in calling and redeeming His people?",
          "type": "multiple-choice",
          "options": [
            "God calls and redeems His people to preserve His name and glory",
            "God only calls the perfect",
            "Redemption is based on human merit",
            "God's name is unimportant in redemption"
          ],
          "correctAnswer": "God calls and redeems His people to preserve His name and glory",
          "explanation": "Verses 9, 11, and 20 show God defers anger, acts for His own name's sake, and redeems Jacob, emphasizing His faithfulness and glory in salvation.",
          "verseReference": "Isaiah 48:9",
          "difficulty": "medium"
        },
        {
          "id": "isaiah-48-medium-q5",
          "question": "What does Isaiah 48 teach about humility and recognizing God's sovereignty?",
          "type": "multiple-choice",
          "options": [
            "God is the first and the last, the creator of earth and heavens",
            "Humans are the center of the universe",
            "God works through idols and images",
            "Sovereignty belongs to kings only"
          ],
          "correctAnswer": "God is the first and the last, the creator of earth and heavens",
          "explanation": "Isaiah 48:12-13 declares God as the first and last who laid the earth's foundation and spans the heavens, calling His people to humility and trust.",
          "verseReference": "Isaiah 48:12",
          "difficulty": "medium"
        },
        {
          "id": "isaiah-48-medium-q6",
          "question": "A believer feels tempted to rely on human wisdom instead of God. What truth from Isaiah 48 counters this temptation?",
          "type": "multiple-choice",
          "options": [
            "Trust in God who reveals hidden things, not idols",
            "Human wisdom is always sufficient",
            "Idols provide true guidance",
            "Secrets should never be shared"
          ],
          "correctAnswer": "Trust in God who reveals hidden things, not idols",
          "explanation": "Isaiah 48:6-8 contrasts God's revelation of new hidden things with the futility of idols, encouraging trust in God’s wisdom rather than human-made images.",
          "verseReference": "Isaiah 48:6",
          "difficulty": "medium"
        },
        {
          "id": "isaiah-48-medium-q7",
          "question": "How does this chapter encourage believers to respond to God’s calling and teaching?",
          "type": "multiple-choice",
          "options": [
            "Listen and follow God’s guidance for profit and direction",
            "Ignore God’s teaching and follow personal desires",
            "Only obey when convenient",
            "Rely on others for spiritual direction only"
          ],
          "correctAnswer": "Listen and follow God’s guidance for profit and direction",
          "explanation": "Isaiah 48:17 presents God as the Redeemer who teaches and leads His people for their profit and right way, urging attentive obedience.",
          "verseReference": "Isaiah 48:17",
          "difficulty": "medium"
        },
        {
          "id": "isaiah-48-medium-q8",
          "question": "What practical teaching about evangelism is found in Isaiah 48 regarding the proclamation of God’s redemption?",
          "type": "multiple-choice",
          "options": [
            "Go forth and declare God’s redemption with a voice of singing to the ends of the earth",
            "Keep the Gospel to yourself",
            "Only evangelize in familiar places",
            "Use force to spread the message"
          ],
          "correctAnswer": "Go forth and declare God’s redemption with a voice of singing to the ends of the earth",
          "explanation": "Isaiah 48:20 commands God’s people to leave Babylon and joyfully declare to all the earth that the LORD has redeemed Jacob, emphasizing bold evangelism.",
          "verseReference": "Isaiah 48:20",
          "difficulty": "medium"
        },
        {
          "id": "isaiah-48-medium-q9",
          "question": "True or False: According to Isaiah 48, God’s anger is entirely removed from His dealings with His people.",
          "type": "true-false",
          "options": [
            "True",
            "False"
          ],
          "correctAnswer": "False",
          "explanation": "Isaiah 48:9 shows God defers His anger for His name's sake, implying anger exists but is restrained out of love and purpose.",
          "verseReference": "Isaiah 48:9",
          "difficulty": "medium"
        },
        {
          "id": "isaiah-48-medium-q10",
          "question": "True or False: Isaiah 48 teaches that there is peace for the wicked according to the LORD.",
          "type": "true-false",
          "options": [
            "True",
            "False"
          ],
          "correctAnswer": "False",
          "explanation": "Isaiah 48:22 clearly states there is no peace for the wicked, underscoring the importance of righteousness.",
          "verseReference": "Isaiah 48:22",
          "difficulty": "medium"
        },
        {
          "id": "isaiah-48-medium-q11",
          "question": "Fill in the blank: Isaiah 48:16 says, 'Come ye near unto me, hear ye this; I have not spoken in _____ from the beginning; from the time that it was, there am I.'",
          "type": "fill-blank",
          "options": [
            "secret",
            "silence",
            "darkness",
            "vain"
          ],
          "correctAnswer": "secret",
          "explanation": "The verse emphasizes God’s openness in revealing His plans from the beginning, countering any idea of secrecy.",
          "verseReference": "Isaiah 48:16",
          "difficulty": "medium"
        },
        {
          "id": "isaiah-48-medium-q12",
          "question": "How does Isaiah 48 describe the people's attitude that God knew before they acted?",
          "type": "multiple-choice",
          "options": [
            "Obstinate and treacherous from the womb",
            "Humble and repentant",
            "Faithful and obedient",
            "Ignorant but well-meaning"
          ],
          "correctAnswer": "Obstinate and treacherous from the womb",
          "explanation": "Isaiah 48:4 and 8 describe the people as obstinate with iron sinews and brass brows, and treacherous from the womb, indicating their stubbornness.",
          "verseReference": "Isaiah 48:4",
          "difficulty": "medium"
        },
        {
          "id": "isaiah-48-medium-q13",
          "question": "What does Isaiah 48 teach about God’s motivation for acting on behalf of His people?",
          "type": "multiple-choice",
          "options": [
            "God acts for His own sake and to protect His name",
            "God acts only when people deserve it",
            "God acts to gain glory from humans",
            "God's actions are random"
          ],
          "correctAnswer": "God acts for His own sake and to protect His name",
          "explanation": "Isaiah 48:11 emphasizes God’s actions are for His own sake to avoid polluting His name and not giving glory to another.",
          "verseReference": "Isaiah 48:11",
          "difficulty": "medium"
        },
        {
          "id": "isaiah-48-medium-q14",
          "question": "A believer struggles with feeling forgotten by God. What assurance does Isaiah 48 offer about God’s ongoing presence?",
          "type": "multiple-choice",
          "options": [
            "God has been present from the beginning and continues to send His Spirit",
            "God forgets those who stray",
            "God only appears in dreams",
            "God is distant and silent"
          ],
          "correctAnswer": "God has been present from the beginning and continues to send His Spirit",
          "explanation": "Isaiah 48:16 says God has not spoken in secret but has been present from the beginning, and now the Lord and His Spirit send His messenger.",
          "verseReference": "Isaiah 48:16",
          "difficulty": "medium"
        },
        {
          "id": "isaiah-48-medium-q15",
          "question": "How does Isaiah 48 illustrate God’s power over creation as a reason for trust and obedience?",
          "type": "multiple-choice",
          "options": [
            "God’s hand laid the earth’s foundation and spanned the heavens",
            "God depends on human strength",
            "Creation happened by chance",
            "God is limited by the heavens"
          ],
          "correctAnswer": "God’s hand laid the earth’s foundation and spanned the heavens",
          "explanation": "Isaiah 48:13 states God laid the earth’s foundation and stretched out the heavens, showing His supreme power worthy of trust.",
          "verseReference": "Isaiah 48:13",
          "difficulty": "medium"
        }
      ],
      "difficulty": "medium",
      "isBookQuiz": false,
      "slug": "isaiah-48-quiz",
      "tags": [
        "isaiah",
        "chapter-48",
        "isaiah",
        "bible-quiz",
        "medium"
      ],
      "totalQuestions": 15,
      "estimatedTime": 12
    },
    "hard": {
      "id": "isaiah-48-hard",
      "title": "Isaiah Chapter 48 Quiz - Hard Level",
      "description": "Challenge yourself with deep analysis and cross-biblical connections from Isaiah Chapter 48.",
      "type": "chapter",
      "book": "Isaiah",
      "chapter": 48,
      "questions": [
        {
          "id": "isaiah-48-hard-q1",
          "question": "In Isaiah 48:3, what literary device is used when God declares 'I have declared the former things from the beginning' and they 'came to pass' suddenly?",
          "type": "multiple-choice",
          "options": [
            "Prophetic foreshadowing",
            "Chiasmus",
            "Typology",
            "Allegory"
          ],
          "correctAnswer": "Prophetic foreshadowing",
          "explanation": "Isaiah 48:3 uses prophetic foreshadowing as God declares events before they happen, emphasizing divine omniscience and sovereignty.",
          "verseReference": "Isaiah 48:3",
          "difficulty": "hard"
        },
        {
          "id": "isaiah-48-hard-q2",
          "question": "According to Isaiah 48:4, what metaphor describes the obstinacy of Israel?",
          "type": "multiple-choice",
          "options": [
            "A neck of iron sinew and a brow of brass",
            "A heart of stone and a tongue of fire",
            "A wall of adamant and a door of bronze",
            "A tree of thorns and a rock of salt"
          ],
          "correctAnswer": "A neck of iron sinew and a brow of brass",
          "explanation": "Isaiah 48:4 uses the metaphor of a neck of iron sinew and a brow of brass to portray Israel's stubbornness and resistance to God's instruction.",
          "verseReference": "Isaiah 48:4",
          "difficulty": "hard"
        },
        {
          "id": "isaiah-48-hard-q3",
          "question": "What is the theological significance of God refining Israel 'not with silver' but 'in the furnace of affliction' as described in Isaiah 48:10?",
          "type": "multiple-choice",
          "options": [
            "It signifies purification through hardship rather than material wealth",
            "It symbolizes the rejection of idolatry",
            "It denotes literal silver refining practices in Israel's history",
            "It refers to a future Messianic judgment"
          ],
          "correctAnswer": "It signifies purification through hardship rather than material wealth",
          "explanation": "Isaiah 48:10 metaphorically describes God's refining of Israel through affliction, highlighting purification by trials instead of material riches.",
          "verseReference": "Isaiah 48:10",
          "difficulty": "hard"
        },
        {
          "id": "isaiah-48-hard-q4",
          "question": "Which phrase in Isaiah 48:12 establishes God's eternal nature and is echoed in Revelation 1:17-18?",
          "type": "multiple-choice",
          "options": [
            "\"I am he; I am the first, I also am the last.\"",
            "\"The LORD of hosts is his name.\"",
            "\"My hand hath laid the foundation of the earth.\"",
            "\"For my name's sake will I defer mine anger.\""
          ],
          "correctAnswer": "\"I am he; I am the first, I also am the last.\"",
          "explanation": "Isaiah 48:12’s phrase ‘I am he; I am the first, I also am the last’ parallels Revelation 1:17-18, underscoring God's eternal and unchanging nature.",
          "verseReference": "Isaiah 48:12",
          "difficulty": "hard"
        },
        {
          "id": "isaiah-48-hard-q5",
          "question": "In Isaiah 48:13, what is the significance of God's hand laying the foundation of the earth and spanning the heavens?",
          "type": "multiple-choice",
          "options": [
            "It affirms God's role as Creator and Sustainer",
            "It refers to Babylonian cosmology",
            "It symbolizes Israel's political power",
            "It describes a future restoration event"
          ],
          "correctAnswer": "It affirms God's role as Creator and Sustainer",
          "explanation": "Isaiah 48:13 emphasizes God’s creative authority and sustaining power over the cosmos, countering idolatrous claims.",
          "verseReference": "Isaiah 48:13",
          "difficulty": "hard"
        },
        {
          "id": "isaiah-48-hard-q6",
          "question": "Isaiah 48:15 speaks of 'I have called him; I have brought him, and he shall make his way prosperous.' Who is this 'him' often interpreted as in biblical typology?",
          "type": "multiple-choice",
          "options": [
            "The Messiah",
            "King Cyrus",
            "The Prophet Isaiah",
            "The nation of Israel"
          ],
          "correctAnswer": "King Cyrus",
          "explanation": "Isaiah 48:15 is frequently interpreted as referring to King Cyrus, whom God calls to fulfill His purposes, foreshadowing Messianic roles.",
          "verseReference": "Isaiah 48:15",
          "difficulty": "hard"
        },
        {
          "id": "isaiah-48-hard-q7",
          "question": "Which Hebrew word concept in Isaiah 48:6, translated as 'hidden things,' underscores God's revelation of previously unknown truths?",
          "type": "multiple-choice",
          "options": [
            "Raz (רָז)",
            "Chokmah (חָכְמָה)",
            "Emet (אֱמֶת)",
            "Shalom (שָׁלוֹם)"
          ],
          "correctAnswer": "Raz (רָז)",
          "explanation": "'Raz' in Isaiah 48:6 refers to mysteries or hidden things God reveals, highlighting divine revelation beyond human understanding.",
          "verseReference": "Isaiah 48:6",
          "difficulty": "hard"
        },
        {
          "id": "isaiah-48-hard-q8",
          "question": "True or False: According to Isaiah 48:22, there is peace for the wicked.",
          "type": "true-false",
          "options": [
            "True",
            "False"
          ],
          "correctAnswer": "False",
          "explanation": "Isaiah 48:22 clearly states 'There is no peace, saith the LORD, unto the wicked,' affirming the absence of peace for the wicked.",
          "verseReference": "Isaiah 48:22",
          "difficulty": "hard"
        },
        {
          "id": "isaiah-48-hard-q9",
          "question": "Isaiah 48:17 calls God 'thy Redeemer, the Holy One of Israel.' How does this title connect to the theme of redemption throughout Isaiah?",
          "type": "multiple-choice",
          "options": [
            "It emphasizes God's role as Savior and Sanctifier of Israel",
            "It refers only to the Exodus event",
            "It is a title used exclusively in Isaiah 48",
            "It denotes a political leader in Israel"
          ],
          "correctAnswer": "It emphasizes God's role as Savior and Sanctifier of Israel",
          "explanation": "Isaiah 48:17’s title highlights God's continuous role in redeeming and sanctifying Israel, a central theme throughout Isaiah.",
          "verseReference": "Isaiah 48:17",
          "difficulty": "hard"
        },
        {
          "id": "isaiah-48-hard-q10",
          "question": "What is the historical context implied in Isaiah 48:20 when it commands to 'Go ye forth of Babylon, flee ye from the Chaldeans'?",
          "type": "multiple-choice",
          "options": [
            "The return of the Jewish exiles from Babylonian captivity",
            "The initial conquest of Babylon by Assyria",
            "The Babylonian siege of Jerusalem",
            "The Roman occupation of Judea"
          ],
          "correctAnswer": "The return of the Jewish exiles from Babylonian captivity",
          "explanation": "Isaiah 48:20 reflects the historical event of Jewish exiles being called to return from Babylonian captivity, marking restoration.",
          "verseReference": "Isaiah 48:20",
          "difficulty": "hard"
        },
        {
          "id": "isaiah-48-hard-q11",
          "question": "How does Isaiah 48:21's imagery of water flowing from the rock connect to the Exodus narrative?",
          "type": "multiple-choice",
          "options": [
            "It alludes to God's provision for Israel in the wilderness",
            "It describes a future Messianic miracle",
            "It is a metaphor for Babylonian irrigation",
            "It refers to the Jordan River crossing"
          ],
          "correctAnswer": "It alludes to God's provision for Israel in the wilderness",
          "explanation": "Isaiah 48:21 recalls the Exodus event where God caused water to flow from the rock, symbolizing divine provision and care.",
          "verseReference": "Isaiah 48:21",
          "difficulty": "hard"
        },
        {
          "id": "isaiah-48-hard-q12",
          "question": "Isaiah 48:11 states, 'I will not give my glory unto another.' What theological principle does this affirm regarding God's uniqueness?",
          "type": "multiple-choice",
          "options": [
            "God’s exclusive sovereignty and glory",
            "The sharing of glory with angels",
            "The equality of gods in the pantheon",
            "The delegation of glory to human kings"
          ],
          "correctAnswer": "God’s exclusive sovereignty and glory",
          "explanation": "Isaiah 48:11 affirms that God alone possesses ultimate glory and will not share it with idols or other beings, emphasizing monotheism.",
          "verseReference": "Isaiah 48:11",
          "difficulty": "hard"
        },
        {
          "id": "isaiah-48-hard-q13",
          "question": "What does the phrase 'mine own sake, even for mine own sake' repeated in Isaiah 48:11 suggest about God's motivations?",
          "type": "multiple-choice",
          "options": [
            "God acts to protect His own reputation and holiness",
            "God is motivated by human actions",
            "God responds to idol worship",
            "God acts solely for Israel's benefit"
          ],
          "correctAnswer": "God acts to protect His own reputation and holiness",
          "explanation": "The repetition in Isaiah 48:11 stresses that God's actions are motivated by preserving His own holy name and glory.",
          "verseReference": "Isaiah 48:11",
          "difficulty": "hard"
        },
        {
          "id": "isaiah-48-hard-q14",
          "question": "According to Isaiah 48:1, what is ironic about Israel's swearing by the name of the LORD and mentioning God of Israel?",
          "type": "multiple-choice",
          "options": [
            "They do so not in truth nor in righteousness",
            "They do so with full understanding",
            "They do it as a genuine expression of faith",
            "They never mention idols"
          ],
          "correctAnswer": "They do so not in truth nor in righteousness",
          "explanation": "Isaiah 48:1 highlights the irony that Israel invokes God's name without genuine faith or righteous behavior.",
          "verseReference": "Isaiah 48:1",
          "difficulty": "hard"
        },
        {
          "id": "isaiah-48-hard-q15",
          "question": "Isaiah 48:16 mentions 'the Lord GOD, and his Spirit, hath sent me.' How does this verse foreshadow New Testament Trinitarian theology?",
          "type": "multiple-choice",
          "options": [
            "It presents a distinction yet unity among the LORD, His Spirit, and the messenger",
            "It denies the existence of the Spirit",
            "It emphasizes only the Father",
            "It refers solely to an angelic being"
          ],
          "correctAnswer": "It presents a distinction yet unity among the LORD, His Spirit, and the messenger",
          "explanation": "Isaiah 48:16 foreshadows the complex unity of God, hinting at Trinitarian relations later clarified in the New Testament.",
          "verseReference": "Isaiah 48:16",
          "difficulty": "hard"
        }
      ],
      "difficulty": "hard",
      "isBookQuiz": false,
      "slug": "isaiah-48-quiz",
      "tags": [
        "isaiah",
        "chapter-48",
        "isaiah",
        "bible-quiz",
        "hard"
      ],
      "totalQuestions": 15,
      "estimatedTime": 15
    },
    "theological": {
      "id": "isaiah-48-theological",
      "title": "Isaiah Chapter 48 Quiz - Theological Level",
      "description": "Deep biblical theology from Isaiah Chapter 48 that unites all believers. Explore foundational truths about God, creation, and humanity.",
      "type": "chapter",
      "book": "Isaiah",
      "chapter": 48,
      "questions": [
        {
          "id": "isaiah-48-theological-q1",
          "question": "According to Isaiah 48, why does God declare the former things from the beginning?",
          "type": "multiple-choice",
          "options": [
            "So that people would not claim their idols caused them",
            "To test the faith of Israel",
            "To frighten the enemies of Israel",
            "To show the greatness of Babylon"
          ],
          "correctAnswer": "So that people would not claim their idols caused them",
          "explanation": "Isaiah 48:3-5 shows God declaring the former things beforehand to prevent people from claiming idols or graven images caused these events. This teaches God's sovereignty over history, consistent with Psalm 19:1 and Acts 2:23.",
          "verseReference": "Isaiah 48:3-5",
          "difficulty": "hard"
        },
        {
          "id": "isaiah-48-theological-q2",
          "question": "What attribute of God is emphasized by His statement, \"I am the first, I also am the last\" in Isaiah 48?",
          "type": "multiple-choice",
          "options": [
            "Eternity and sovereignty",
            "Compassion and mercy",
            "Wrath and judgment",
            "Creation and destruction"
          ],
          "correctAnswer": "Eternity and sovereignty",
          "explanation": "Isaiah 48:12 highlights God's eternal existence and absolute sovereignty, a theme echoed in Revelation 1:17-18 and Isaiah 44:6, affirming God's unchanging nature and lordship over all time.",
          "verseReference": "Isaiah 48:12",
          "difficulty": "hard"
        },
        {
          "id": "isaiah-48-theological-q3",
          "question": "In Isaiah 48, how does God describe Israel's spiritual condition before His refining?",
          "type": "multiple-choice",
          "options": [
            "Obstinate with an iron sinew and brow of brass",
            "Pure and faithful servants",
            "Gentle and humble followers",
            "Wise and understanding people"
          ],
          "correctAnswer": "Obstinate with an iron sinew and brow of brass",
          "explanation": "Isaiah 48:4 uses the metaphor of an iron sinew and brass brow to depict Israel's stubbornness and hardness of heart, consistent with Jeremiah 17:9 and Romans 1:21 highlighting human sinfulness.",
          "verseReference": "Isaiah 48:4",
          "difficulty": "hard"
        },
        {
          "id": "isaiah-48-theological-q4",
          "question": "What reason does God give in Isaiah 48 for refraining His anger and not cutting Israel off?",
          "type": "multiple-choice",
          "options": [
            "For His name's sake and for His praise",
            "Because Israel repented fully",
            "Due to the intercession of the prophets",
            "Because Babylon was more wicked"
          ],
          "correctAnswer": "For His name's sake and for His praise",
          "explanation": "Isaiah 48:9 states God defers anger for His own name’s sake and praise, reflecting divine holiness and faithfulness, parallel to Exodus 34:5-7 and Ezekiel 36:22-23.",
          "verseReference": "Isaiah 48:9",
          "difficulty": "hard"
        },
        {
          "id": "isaiah-48-theological-q5",
          "question": "According to Isaiah 48, what metaphor does God use to describe the process by which He has refined Israel?",
          "type": "multiple-choice",
          "options": [
            "Chosen in the furnace of affliction",
            "Led like sheep to pasture",
            "Washed clean in rivers of water",
            "Anointed with holy oil"
          ],
          "correctAnswer": "Chosen in the furnace of affliction",
          "explanation": "Isaiah 48:10 describes God's refining of Israel through affliction, symbolized as a furnace, a metaphor for purification found also in Malachi 3:3 and 1 Peter 1:6-7.",
          "verseReference": "Isaiah 48:10",
          "difficulty": "hard"
        },
        {
          "id": "isaiah-48-theological-q6",
          "question": "Who is identified as having laid the foundations of the earth and spanned the heavens in Isaiah 48?",
          "type": "multiple-choice",
          "options": [
            "The LORD",
            "Babylon's king",
            "The Chaldeans",
            "The prophets"
          ],
          "correctAnswer": "The LORD",
          "explanation": "Isaiah 48:13 attributes creation to the LORD, affirming His omnipotence and creative authority, consistent with Genesis 1:1, Psalm 102:25-27, and John 1:3.",
          "verseReference": "Isaiah 48:13",
          "difficulty": "hard"
        },
        {
          "id": "isaiah-48-theological-q7",
          "question": "What does God declare as the reason He will not give His glory to another in Isaiah 48?",
          "type": "multiple-choice",
          "options": [
            "For His own sake and to avoid polluting His name",
            "Because no one else is worthy",
            "To honor the temple in Jerusalem",
            "To exalt the kings of Israel"
          ],
          "correctAnswer": "For His own sake and to avoid polluting His name",
          "explanation": "Isaiah 48:11 emphasizes God's concern for His own glory and name, highlighting the doctrine of divine holiness and uniqueness, paralleled in Isaiah 42:8 and Philippians 2:9-11.",
          "verseReference": "Isaiah 48:11",
          "difficulty": "hard"
        },
        {
          "id": "isaiah-48-theological-q8",
          "question": "How does Isaiah 48 describe the new things God has shown Israel?",
          "type": "multiple-choice",
          "options": [
            "Hidden things from this time not known before",
            "Prophecies about the destruction of Babylon",
            "Laws for ritual purity",
            "Songs of praise for the temple"
          ],
          "correctAnswer": "Hidden things from this time not known before",
          "explanation": "Isaiah 48:6 reveals God showing new, previously hidden things to Israel, signifying progressive revelation, consistent with Hebrews 1:1-2 and Jeremiah 33:3.",
          "verseReference": "Isaiah 48:6",
          "difficulty": "hard"
        },
        {
          "id": "isaiah-48-theological-q9",
          "question": "What does Isaiah 48 say about the wicked in relation to peace?",
          "type": "multiple-choice",
          "options": [
            "There is no peace for the wicked",
            "They will find peace through repentance",
            "Peace comes after judgment",
            "Peace is granted to all"
          ],
          "correctAnswer": "There is no peace for the wicked",
          "explanation": "Isaiah 48:22 declares no peace for the wicked, affirming the biblical doctrine of divine justice and separation from God’s peace, corroborated by Romans 3:17 and Proverbs 1:33.",
          "verseReference": "Isaiah 48:22",
          "difficulty": "hard"
        },
        {
          "id": "isaiah-48-theological-q10",
          "question": "In Isaiah 48, who is referred to as God's servant that the LORD has redeemed?",
          "type": "multiple-choice",
          "options": [
            "Jacob",
            "Babylon",
            "The Chaldeans",
            "The prophets"
          ],
          "correctAnswer": "Jacob",
          "explanation": "Isaiah 48:20 speaks of the LORD redeeming His servant Jacob, symbolizing the nation of Israel, consistent with Isaiah 44:1 and Luke 1:54-55.",
          "verseReference": "Isaiah 48:20",
          "difficulty": "hard"
        },
        {
          "id": "isaiah-48-theological-q11",
          "question": "What role does the Spirit have according to Isaiah 48:16?",
          "type": "multiple-choice",
          "options": [
            "Sent by the Lord GOD alongside Him to the people",
            "A judgment upon Babylon",
            "A spirit of confusion among enemies",
            "The giver of the law"
          ],
          "correctAnswer": "Sent by the Lord GOD alongside Him to the people",
          "explanation": "Isaiah 48:16 mentions the Lord GOD and His Spirit sent together, indicating the cooperative work of the Spirit in divine revelation and mission, in line with John 14:26 and Acts 1:8.",
          "verseReference": "Isaiah 48:16",
          "difficulty": "hard"
        },
        {
          "id": "isaiah-48-theological-q12",
          "question": "What is the consequence of not hearkening to God's commandments as stated in Isaiah 48?",
          "type": "multiple-choice",
          "options": [
            "Loss of peace and righteousness",
            "Immediate destruction",
            "Exile to Babylon",
            "Blessing of prosperity"
          ],
          "correctAnswer": "Loss of peace and righteousness",
          "explanation": "Isaiah 48:18 stresses that if Israel had obeyed, their peace would be like a river and righteousness like the waves of the sea, implying disobedience results in loss of these blessings, consistent with Psalm 119:165 and John 14:27.",
          "verseReference": "Isaiah 48:18",
          "difficulty": "hard"
        },
        {
          "id": "isaiah-48-theological-q13",
          "question": "How does Isaiah 48 describe Israel's offspring if they had obeyed God's commands?",
          "type": "multiple-choice",
          "options": [
            "As numerous as the sand and gravel, not cut off",
            "Scattered and diminished",
            "Like a few stars in the sky",
            "Hidden like a treasure"
          ],
          "correctAnswer": "As numerous as the sand and gravel, not cut off",
          "explanation": "Isaiah 48:19 promises that obedience would have resulted in Israel’s seed being as the sand and gravel, a metaphor for great and enduring multiplication, seen also in Genesis 22:17 and Hebrews 11:12.",
          "verseReference": "Isaiah 48:19",
          "difficulty": "hard"
        },
        {
          "id": "isaiah-48-theological-q14",
          "question": "What divine action is recalled in Isaiah 48 about God's provision during the desert journey?",
          "type": "multiple-choice",
          "options": [
            "Causing waters to flow from the rock",
            "Sending manna from heaven",
            "Leading with a pillar of fire",
            "Parting the Red Sea"
          ],
          "correctAnswer": "Causing waters to flow from the rock",
          "explanation": "Isaiah 48:21 recalls God causing waters to flow from the rock during Israel's desert journey, illustrating God's providence, as also seen in Exodus 17:6 and 1 Corinthians 10:4.",
          "verseReference": "Isaiah 48:21",
          "difficulty": "hard"
        },
        {
          "id": "isaiah-48-theological-q15",
          "question": "Who does Isaiah 48 identify as the Redeemer and Holy One of Israel who teaches and leads?",
          "type": "multiple-choice",
          "options": [
            "The LORD, thy God",
            "The king of Babylon",
            "The priest of Jerusalem",
            "The angel of the covenant"
          ],
          "correctAnswer": "The LORD, thy God",
          "explanation": "Isaiah 48:17 identifies the LORD as Redeemer and Holy One who teaches and leads Israel, affirming God's role as Savior and Shepherd, consistent with Psalm 23 and John 10:11.",
          "verseReference": "Isaiah 48:17",
          "difficulty": "hard"
        }
      ],
      "difficulty": "hard",
      "isBookQuiz": false,
      "slug": "isaiah-48-quiz",
      "tags": [
        "isaiah",
        "chapter-48",
        "isaiah",
        "bible-quiz",
        "theological"
      ],
      "totalQuestions": 15,
      "estimatedTime": 25
    }
  }
}