{
  "id": "jeremiah-44-tabbed",
  "title": "Jeremiah Chapter 44 Quiz - Multi-Level",
  "description": "An enhanced quiz on Jeremiah chapter 44 with Easy, Medium, Hard, and Theological levels. Each level has 15 carefully crafted questions. Choose your difficulty and dive in!",
  "tabs": {
    "easy": {
      "id": "jeremiah-44-easy",
      "title": "Jeremiah Chapter 44 Quiz - Easy Level",
      "description": "Perfect for beginners! Test your basic knowledge of Jeremiah Chapter 44.",
      "type": "chapter",
      "book": "Jeremiah",
      "chapter": 44,
      "questions": [
        {
          "id": "jeremiah-44-easy-q1",
          "question": "According to Jeremiah 44:1, where were the Jews dwelling when Jeremiah received the word from the LORD?",
          "type": "multiple-choice",
          "options": [
            "Egypt",
            "Babylon",
            "Jerusalem",
            "Assyria"
          ],
          "correctAnswer": "Egypt",
          "explanation": "Jeremiah 44:1 states the word came to Jeremiah concerning all the Jews dwelling in the land of Egypt.",
          "verseReference": "Jeremiah 44:1",
          "difficulty": "easy"
        },
        {
          "id": "jeremiah-44-easy-q2",
          "question": "What cities are mentioned in Jeremiah 44:1 where the Jews dwelt in Egypt?",
          "type": "multiple-choice",
          "options": [
            "Migdol, Tahpanhes, Noph, Pathros",
            "Jericho, Hebron, Bethlehem, Nazareth",
            "Tyre, Sidon, Gaza, Ashkelon",
            "Babylon, Nineveh, Damascus, Susa"
          ],
          "correctAnswer": "Migdol, Tahpanhes, Noph, Pathros",
          "explanation": "Jeremiah 44:1 lists these cities as where the Jews were dwelling in Egypt.",
          "verseReference": "Jeremiah 44:1",
          "difficulty": "easy"
        },
        {
          "id": "jeremiah-44-easy-q3",
          "question": "Why were Jerusalem and the cities of Judah desolate according to Jeremiah 44:2?",
          "type": "multiple-choice",
          "options": [
            "Because of their wickedness",
            "Because of a famine",
            "Because of a flood",
            "Because of a war with Egypt"
          ],
          "correctAnswer": "Because of their wickedness",
          "explanation": "Jeremiah 44:2 explains the desolation was due to the evil the LORD brought upon them because of their wickedness.",
          "verseReference": "Jeremiah 44:2",
          "difficulty": "easy"
        },
        {
          "id": "jeremiah-44-easy-q4",
          "question": "What wicked act did the people commit that provoked God to anger as stated in Jeremiah 44:3?",
          "type": "multiple-choice",
          "options": [
            "Burning incense to other gods",
            "Stealing from the poor",
            "Breaking the Sabbath",
            "Ignoring the prophets"
          ],
          "correctAnswer": "Burning incense to other gods",
          "explanation": "Jeremiah 44:3 mentions they burned incense and served other gods which provoked God's anger.",
          "verseReference": "Jeremiah 44:3",
          "difficulty": "easy"
        },
        {
          "id": "jeremiah-44-easy-q5",
          "question": "Who did God send to warn the people not to commit abominable acts, according to Jeremiah 44:4?",
          "type": "multiple-choice",
          "options": [
            "His servants the prophets",
            "His angels",
            "His priests",
            "The kings of Judah"
          ],
          "correctAnswer": "His servants the prophets",
          "explanation": "Jeremiah 44:4 says God sent all His servants the prophets to warn the people.",
          "verseReference": "Jeremiah 44:4",
          "difficulty": "easy"
        },
        {
          "id": "jeremiah-44-easy-q6",
          "question": "What was the people's response to the prophets' warnings as described in Jeremiah 44:5?",
          "type": "multiple-choice",
          "options": [
            "They did not listen",
            "They repented",
            "They fled to Egypt",
            "They imprisoned the prophets"
          ],
          "correctAnswer": "They did not listen",
          "explanation": "Jeremiah 44:5 states they hearkened not nor inclined their ear to turn from their wickedness.",
          "verseReference": "Jeremiah 44:5",
          "difficulty": "easy"
        },
        {
          "id": "jeremiah-44-easy-q7",
          "question": "According to Jeremiah 44:7, what great evil were the people committing against their souls?",
          "type": "multiple-choice",
          "options": [
            "Cutting off man, woman, child, and suckling from Judah",
            "Building idols",
            "Stealing from the temple",
            "Harming the prophets"
          ],
          "correctAnswer": "Cutting off man, woman, child, and suckling from Judah",
          "explanation": "Jeremiah 44:7 says they were committing great evil to cut off all from Judah to leave none to remain.",
          "verseReference": "Jeremiah 44:7",
          "difficulty": "easy"
        },
        {
          "id": "jeremiah-44-easy-q8",
          "question": "What did the people say about burning incense to the queen of heaven in Jeremiah 44:17?",
          "type": "multiple-choice",
          "options": [
            "They would continue to do so",
            "They would stop immediately",
            "They did it only once",
            "They did not believe in the queen of heaven"
          ],
          "correctAnswer": "They would continue to do so",
          "explanation": "Jeremiah 44:17 records the people saying they will certainly burn incense to the queen of heaven as before.",
          "verseReference": "Jeremiah 44:17",
          "difficulty": "easy"
        },
        {
          "id": "jeremiah-44-easy-q9",
          "question": "What did the people claim happened when they burned incense to the queen of heaven, according to Jeremiah 44:18?",
          "type": "multiple-choice",
          "options": [
            "They had plenty and were well",
            "They were cursed",
            "They were attacked by enemies",
            "They were exiled"
          ],
          "correctAnswer": "They had plenty and were well",
          "explanation": "Jeremiah 44:17-18 show they said when they burned incense to the queen of heaven they were well and had plenty.",
          "verseReference": "Jeremiah 44:17",
          "difficulty": "easy"
        },
        {
          "id": "jeremiah-44-easy-q10",
          "question": "True or False: Jeremiah 44:11 says the LORD will set His face for good upon the people of Judah.",
          "type": "true-false",
          "options": [
            "True",
            "False"
          ],
          "correctAnswer": "False",
          "explanation": "Jeremiah 44:11 says God will set His face against them for evil and to cut off all Judah.",
          "verseReference": "Jeremiah 44:11",
          "difficulty": "easy"
        },
        {
          "id": "jeremiah-44-easy-q11",
          "question": "True or False: Jeremiah 44:16 shows the people promised to obey Jeremiah's words from the LORD.",
          "type": "true-false",
          "options": [
            "True",
            "False"
          ],
          "correctAnswer": "False",
          "explanation": "Jeremiah 44:16 records the people saying they will not hearken unto Jeremiah's words.",
          "verseReference": "Jeremiah 44:16",
          "difficulty": "easy"
        },
        {
          "id": "jeremiah-44-easy-q12",
          "question": "True or False: Jeremiah 44:28 predicts that a small number will escape the sword and return to Judah from Egypt.",
          "type": "true-false",
          "options": [
            "True",
            "False"
          ],
          "correctAnswer": "True",
          "explanation": "Jeremiah 44:28 states that a small number that escape the sword shall return from Egypt to Judah.",
          "verseReference": "Jeremiah 44:28",
          "difficulty": "easy"
        },
        {
          "id": "jeremiah-44-easy-q13",
          "question": "Complete this verse from Jeremiah 44:30: 'Thus saith the LORD; Behold, I will give Pharaohhophra king of Egypt into the hand of his ______.'",
          "type": "fill-blank",
          "options": [
            "enemies",
            "friends",
            "priests",
            "prophets"
          ],
          "correctAnswer": "enemies",
          "explanation": "Jeremiah 44:30 says Pharaohhophra will be given into the hand of his enemies.",
          "verseReference": "Jeremiah 44:30",
          "difficulty": "easy"
        },
        {
          "id": "jeremiah-44-easy-q14",
          "question": "What did Jeremiah say about the incense burned by the people and their ancestors in Jerusalem, according to Jeremiah 44:21?",
          "type": "multiple-choice",
          "options": [
            "The LORD remembered it and was grieved",
            "The LORD ignored it",
            "The LORD accepted it",
            "The LORD blessed the people"
          ],
          "correctAnswer": "The LORD remembered it and was grieved",
          "explanation": "Jeremiah 44:21-22 shows the LORD could no longer bear their evil and abominations, causing desolation.",
          "verseReference": "Jeremiah 44:21",
          "difficulty": "easy"
        },
        {
          "id": "jeremiah-44-easy-q15",
          "question": "According to Jeremiah 44:26, what did the LORD swear about His name in the land of Egypt?",
          "type": "multiple-choice",
          "options": [
            "His name shall no more be named in the mouth of any man of Judah",
            "His name would be honored by all",
            "His name would be made famous",
            "His name would be praised daily"
          ],
          "correctAnswer": "His name shall no more be named in the mouth of any man of Judah",
          "explanation": "Jeremiah 44:26 declares that God swore His name would not be named by Judah in Egypt.",
          "verseReference": "Jeremiah 44:26",
          "difficulty": "easy"
        }
      ],
      "difficulty": "easy",
      "isBookQuiz": false,
      "slug": "jeremiah-44-quiz",
      "tags": [
        "jeremiah",
        "chapter-44",
        "jeremiah",
        "bible-quiz",
        "easy"
      ],
      "totalQuestions": 15,
      "estimatedTime": 8
    },
    "medium": {
      "id": "jeremiah-44-medium",
      "title": "Jeremiah Chapter 44 Quiz - Medium Level",
      "description": "Ready for more? Apply biblical truths from Jeremiah Chapter 44 to real-life situations.",
      "type": "chapter",
      "book": "Jeremiah",
      "chapter": 44,
      "questions": [
        {
          "id": "jeremiah-44-medium-q1",
          "question": "A fellow believer is struggling with temptation to serve other gods. Based on Jeremiah 44, what biblical truth would you share about obedience?",
          "type": "multiple-choice",
          "options": [
            "Obedience to God's Word means avoiding idolatry and worshiping only the LORD.",
            "It is acceptable to worship other gods if it brings peace.",
            "Ignoring God's commands has no real consequences.",
            "Serving other gods is a personal choice without spiritual impact."
          ],
          "correctAnswer": "Obedience to God's Word means avoiding idolatry and worshiping only the LORD.",
          "explanation": "Jeremiah 44:3-5, 22-23 emphasize the sin of burning incense to other gods and the call to not do this abominable thing. God's anger comes because they have not obeyed His voice or statutes.",
          "verseReference": "Jeremiah 44:3",
          "difficulty": "medium"
        },
        {
          "id": "jeremiah-44-medium-q2",
          "question": "How does Jeremiah 44 teach us about trusting God's discipline during hard times?",
          "type": "multiple-choice",
          "options": [
            "God's discipline comes because of our sin and is meant to bring us to repentance.",
            "Hard times mean God has abandoned us completely.",
            "We should ignore discipline and do as we please.",
            "Suffering is always random and unrelated to spiritual condition."
          ],
          "correctAnswer": "God's discipline comes because of our sin and is meant to bring us to repentance.",
          "explanation": "Verses 2, 6, and 22 show God bringing desolation because of wickedness, and Jeremiah warns that this is due to their rebellion. Discipline is a consequence of sin and calls for repentance.",
          "verseReference": "Jeremiah 44:2",
          "difficulty": "medium"
        },
        {
          "id": "jeremiah-44-medium-q3",
          "question": "A believer asks how to be faithful in prayer and devotion. What lesson does Jeremiah 44 offer about sincere worship?",
          "type": "multiple-choice",
          "options": [
            "True worship honors God alone and does not mix with idolatry.",
            "Any form of worship is acceptable if it feels sincere.",
            "Worship is optional and not necessary for a faithful life.",
            "God is indifferent to how we worship Him."
          ],
          "correctAnswer": "True worship honors God alone and does not mix with idolatry.",
          "explanation": "Jeremiah 44:4-5 and 21-23 show God’s hatred for incense burned to other gods and that true worship requires obedience to His law and statutes.",
          "verseReference": "Jeremiah 44:4",
          "difficulty": "medium"
        },
        {
          "id": "jeremiah-44-medium-q4",
          "question": "What does Jeremiah 44 teach about humility and repentance when facing consequences of sin?",
          "type": "multiple-choice",
          "options": [
            "Humility involves recognizing our sin and turning back to God.",
            "Pride and stubbornness protect us from God’s judgment.",
            "Ignoring sin leads to God’s favor.",
            "Repentance is unnecessary if we feel innocent."
          ],
          "correctAnswer": "Humility involves recognizing our sin and turning back to God.",
          "explanation": "Verses 9-10 reveal that the people were not humbled or fearful of God’s law, leading to judgment. Humility would mean fear of God and walking in His statutes.",
          "verseReference": "Jeremiah 44:10",
          "difficulty": "medium"
        },
        {
          "id": "jeremiah-44-medium-q5",
          "question": "A believer wonders about perseverance through trials. What does Jeremiah 44 say about God’s ultimate control and purpose?",
          "type": "multiple-choice",
          "options": [
            "God controls all events, including trials, to fulfill His purposes and bring about repentance.",
            "Trials are random and have no spiritual significance.",
            "God abandons those who suffer.",
            "We can avoid trials by ignoring God’s commands."
          ],
          "correctAnswer": "God controls all events, including trials, to fulfill His purposes and bring about repentance.",
          "explanation": "Jeremiah 44:11-14 and 26-28 show God’s sovereign judgment on those who rebel, yet He preserves a remnant to demonstrate His word’s truth.",
          "verseReference": "Jeremiah 44:11",
          "difficulty": "medium"
        },
        {
          "id": "jeremiah-44-medium-q6",
          "question": "Based on Jeremiah 44, how should believers respond to the temptation of cultural or family pressures to compromise faith?",
          "type": "multiple-choice",
          "options": [
            "They should obey God’s commands even if family and culture oppose.",
            "They should conform to cultural practices to avoid conflict.",
            "Faith can be adapted to fit family traditions.",
            "Ignoring God’s Word is acceptable to maintain peace."
          ],
          "correctAnswer": "They should obey God’s commands even if family and culture oppose.",
          "explanation": "Jeremiah 44:15-18 shows the people’s stubbornness in following idolatry despite Jeremiah’s warnings, illustrating the danger of conforming to cultural pressure over God’s Word.",
          "verseReference": "Jeremiah 44:15",
          "difficulty": "medium"
        },
        {
          "id": "jeremiah-44-medium-q7",
          "question": "How does Jeremiah 44 encourage integrity and honesty in spiritual commitments?",
          "type": "multiple-choice",
          "options": [
            "Fulfill vows made to God and be truthful in devotion.",
            "It’s acceptable to break vows if convenient.",
            "Vows are unimportant and can be ignored.",
            "Honesty in spiritual matters is optional."
          ],
          "correctAnswer": "Fulfill vows made to God and be truthful in devotion.",
          "explanation": "Jeremiah 44:25 highlights the people's vow to continue burning incense, showing the seriousness of vows and the expectation to perform them faithfully.",
          "verseReference": "Jeremiah 44:25",
          "difficulty": "medium"
        },
        {
          "id": "jeremiah-44-medium-q8",
          "question": "True or False: Jeremiah 44 teaches that God will protect those who disobey Him and worship other gods.",
          "type": "true-false",
          "options": [
            "True",
            "False"
          ],
          "correctAnswer": "False",
          "explanation": "Jeremiah 44:7-13 clearly states that God’s anger will bring destruction upon those who burn incense to other gods and disobey Him.",
          "verseReference": "Jeremiah 44:7",
          "difficulty": "medium"
        },
        {
          "id": "jeremiah-44-medium-q9",
          "question": "True or False: Jeremiah 44 indicates that a small number who repent may be spared and return to their land.",
          "type": "true-false",
          "options": [
            "True",
            "False"
          ],
          "correctAnswer": "True",
          "explanation": "Verse 28 promises that a small remnant will escape the sword and return to Judah, demonstrating God's mercy towards some who repent.",
          "verseReference": "Jeremiah 44:28",
          "difficulty": "medium"
        },
        {
          "id": "jeremiah-44-medium-q10",
          "question": "A believer asks about the consequences of unrepentant sin in family and community. What does Jeremiah 44 teach?",
          "type": "multiple-choice",
          "options": [
            "Unrepentant sin leads to destruction of families and communities.",
            "Sin in a few members does not affect the whole community.",
            "God ignores persistent communal sin.",
            "Only individual sin matters, not collective sin."
          ],
          "correctAnswer": "Unrepentant sin leads to destruction of families and communities.",
          "explanation": "Jeremiah 44:7-8 and 12-14 describe how the entire remnant in Egypt faces destruction because of their collective sin in idolatry and disobedience.",
          "verseReference": "Jeremiah 44:7",
          "difficulty": "medium"
        },
        {
          "id": "jeremiah-44-medium-q11",
          "question": "Fill in the blank: Jeremiah 44 teaches that the people burned incense to the ____ of heaven.",
          "type": "fill-blank",
          "options": [
            "queen",
            "king",
            "prince",
            "angel"
          ],
          "correctAnswer": "queen",
          "explanation": "Jeremiah 44:17 and 25 mention the people burning incense to the queen of heaven, which is condemned in this passage.",
          "verseReference": "Jeremiah 44:17",
          "difficulty": "medium"
        },
        {
          "id": "jeremiah-44-medium-q12",
          "question": "How does Jeremiah 44 illustrate the importance of trusting God’s Word over human reasoning?",
          "type": "multiple-choice",
          "options": [
            "God’s Word will stand and prove true despite human doubts and rebellion.",
            "Human opinion is more important than God’s Word.",
            "God’s Word is flexible and changes to fit culture.",
            "We should ignore God’s Word if it conflicts with our desires."
          ],
          "correctAnswer": "God’s Word will stand and prove true despite human doubts and rebellion.",
          "explanation": "Verses 28-29 emphasize that the remnant will know whose words stand, God’s or theirs, underscoring the reliability and truth of God’s Word.",
          "verseReference": "Jeremiah 44:29",
          "difficulty": "medium"
        },
        {
          "id": "jeremiah-44-medium-q13",
          "question": "What does Jeremiah 44 teach about sharing the gospel or warning others about sin?",
          "type": "multiple-choice",
          "options": [
            "We must faithfully warn others even if they refuse to listen.",
            "It is better to keep silent to avoid conflict.",
            "People will always accept our warnings if we share gently.",
            "Warning others about sin is unnecessary in modern times."
          ],
          "correctAnswer": "We must faithfully warn others even if they refuse to listen.",
          "explanation": "Jeremiah 44:4-5 and 20-24 show Jeremiah faithfully delivering God’s message despite rejection, modeling obedience in evangelism and warning.",
          "verseReference": "Jeremiah 44:4",
          "difficulty": "medium"
        },
        {
          "id": "jeremiah-44-medium-q14",
          "question": "A believer is struggling with contentment amid loss. How does Jeremiah 44 help in understanding God’s purpose in trials?",
          "type": "multiple-choice",
          "options": [
            "Trials often come as consequences of sin to call us to repentance and restoration.",
            "Loss means God is punishing us without hope.",
            "Contentment comes by ignoring God during trials.",
            "Trials are random and without purpose."
          ],
          "correctAnswer": "Trials often come as consequences of sin to call us to repentance and restoration.",
          "explanation": "Jeremiah 44:6 and 22-23 connect suffering from famine and sword to God’s judgment for sin, implying the call to humble repentance.",
          "verseReference": "Jeremiah 44:6",
          "difficulty": "medium"
        },
        {
          "id": "jeremiah-44-medium-q15",
          "question": "What is a key lesson about family life and parenting from the disobedience described in Jeremiah 44?",
          "type": "multiple-choice",
          "options": [
            "Teaching children to obey God’s law is crucial to avoid generational sin.",
            "Family traditions can replace obedience to God.",
            "Parental influence has no spiritual impact on children.",
            "Children will naturally follow God without guidance."
          ],
          "correctAnswer": "Teaching children to obey God’s law is crucial to avoid generational sin.",
          "explanation": "Jeremiah 44:3, 9-10 highlight that the people and their fathers provoked God by idolatry, showing the importance of faithful teaching across generations.",
          "verseReference": "Jeremiah 44:3",
          "difficulty": "medium"
        }
      ],
      "difficulty": "medium",
      "isBookQuiz": false,
      "slug": "jeremiah-44-quiz",
      "tags": [
        "jeremiah",
        "chapter-44",
        "jeremiah",
        "bible-quiz",
        "medium"
      ],
      "totalQuestions": 15,
      "estimatedTime": 12
    },
    "hard": {
      "id": "jeremiah-44-hard",
      "title": "Jeremiah Chapter 44 Quiz - Hard Level",
      "description": "Challenge yourself with deep analysis and cross-biblical connections from Jeremiah Chapter 44.",
      "type": "chapter",
      "book": "Jeremiah",
      "chapter": 44,
      "questions": [
        {
          "id": "jeremiah-44-hard-q1",
          "question": "According to Jeremiah 44, why were the cities of Judah and Jerusalem left desolate?",
          "type": "multiple-choice",
          "options": [
            "Because of their wickedness in serving other gods",
            "Due to a foreign invasion alone",
            "Because of a natural disaster",
            "Because of famine only"
          ],
          "correctAnswer": "Because of their wickedness in serving other gods",
          "explanation": "Jeremiah 44:2-3 explains that the desolation was due to the wickedness of the people who provoked God by burning incense and serving other gods.",
          "verseReference": "Jeremiah 44:2-3",
          "difficulty": "hard"
        },
        {
          "id": "jeremiah-44-hard-q2",
          "question": "What was the LORD's response to the people's continued idolatry despite the prophets' warnings?",
          "type": "multiple-choice",
          "options": [
            "His fury and anger were poured forth, resulting in destruction",
            "He sent an angel to protect them",
            "He forgave them immediately",
            "He relocated them to another land"
          ],
          "correctAnswer": "His fury and anger were poured forth, resulting in destruction",
          "explanation": "Jeremiah 44:6 states that because the people did not listen, God's fury was kindled and cities became wasted and desolate.",
          "verseReference": "Jeremiah 44:6",
          "difficulty": "hard"
        },
        {
          "id": "jeremiah-44-hard-q3",
          "question": "In Jeremiah 44, what specific action by the Jews in Egypt provokes God's wrath further?",
          "type": "multiple-choice",
          "options": [
            "Burning incense to other gods in the land of Egypt",
            "Building altars to the LORD",
            "Offering sacrifices to the LORD",
            "Restoring the temple in Jerusalem"
          ],
          "correctAnswer": "Burning incense to other gods in the land of Egypt",
          "explanation": "Jeremiah 44:8 highlights that the people provoked God by burning incense to other gods after fleeing to Egypt.",
          "verseReference": "Jeremiah 44:8",
          "difficulty": "hard"
        },
        {
          "id": "jeremiah-44-hard-q4",
          "question": "What does Jeremiah say will happen to the remnant of Judah living in Egypt according to Jeremiah 44?",
          "type": "multiple-choice",
          "options": [
            "They will be consumed by sword and famine and become a curse",
            "They will prosper and multiply",
            "They will conquer Egypt",
            "They will build a new temple"
          ],
          "correctAnswer": "They will be consumed by sword and famine and become a curse",
          "explanation": "Jeremiah 44:12 explains that the remnant in Egypt will be consumed and become an execration and reproach.",
          "verseReference": "Jeremiah 44:12",
          "difficulty": "hard"
        },
        {
          "id": "jeremiah-44-hard-q5",
          "question": "What is the people's response to Jeremiah's prophecy about ceasing to worship the queen of heaven?",
          "type": "multiple-choice",
          "options": [
            "They refuse and pledge to continue their worship",
            "They agree and repent immediately",
            "They ask for a sign to confirm the prophecy",
            "They exile Jeremiah"
          ],
          "correctAnswer": "They refuse and pledge to continue their worship",
          "explanation": "Jeremiah 44:16-17 records the people insisting on continuing their worship of the queen of heaven despite Jeremiah's warnings.",
          "verseReference": "Jeremiah 44:16-17",
          "difficulty": "hard"
        },
        {
          "id": "jeremiah-44-hard-q6",
          "question": "What reason do the people give for their worship of the queen of heaven in Jeremiah 44?",
          "type": "multiple-choice",
          "options": [
            "They had plenty of food and were well during those times",
            "They wanted to align with Egyptian customs",
            "They were commanded by their priests",
            "They sought political alliances"
          ],
          "correctAnswer": "They had plenty of food and were well during those times",
          "explanation": "Jeremiah 44:17 states that they associate their prosperity with worshipping the queen of heaven.",
          "verseReference": "Jeremiah 44:17",
          "difficulty": "hard"
        },
        {
          "id": "jeremiah-44-hard-q7",
          "question": "How does Jeremiah respond to the people's justification for worshipping the queen of heaven?",
          "type": "multiple-choice",
          "options": [
            "He reminds them that their land was desolate because of their sin",
            "He agrees that their prosperity was due to her",
            "He suggests a compromise worship",
            "He tells them to seek help from Egypt"
          ],
          "correctAnswer": "He reminds them that their land was desolate because of their sin",
          "explanation": "Jeremiah 44:21-22 explains that God could no longer bear their evil and that their land became a desolation due to their sins.",
          "verseReference": "Jeremiah 44:21-22",
          "difficulty": "hard"
        },
        {
          "id": "jeremiah-44-hard-q8",
          "question": "What does the LORD declare concerning His name among the Jews living in Egypt?",
          "type": "multiple-choice",
          "options": [
            "His name will no longer be named among them",
            "His name will be honored above all gods",
            "His name will be proclaimed in their temples",
            "His name will be written on their hearts"
          ],
          "correctAnswer": "His name will no longer be named among them",
          "explanation": "Jeremiah 44:26 states that God swore His name would no longer be named by any man of Judah in Egypt.",
          "verseReference": "Jeremiah 44:26",
          "difficulty": "hard"
        },
        {
          "id": "jeremiah-44-hard-q9",
          "question": "What fate does Jeremiah foretell for Pharaohhophra, king of Egypt?",
          "type": "multiple-choice",
          "options": [
            "He will be delivered into the hands of his enemies",
            "He will reign peacefully for many years",
            "He will form an alliance with Judah",
            "He will be victorious over Babylon"
          ],
          "correctAnswer": "He will be delivered into the hands of his enemies",
          "explanation": "Jeremiah 44:30 prophesies Pharaohhophra will be given into the hands of those who seek his life, similar to Zedekiah's fate.",
          "verseReference": "Jeremiah 44:30",
          "difficulty": "hard"
        },
        {
          "id": "jeremiah-44-hard-q10",
          "question": "True or False: Jeremiah 44 records that the people humbled themselves and obeyed God's law after the destruction of Jerusalem.",
          "type": "true-false",
          "options": [
            "True",
            "False"
          ],
          "correctAnswer": "False",
          "explanation": "Jeremiah 44:10 clearly states that the people were not humbled, did not fear God, nor walk in His law or statutes.",
          "verseReference": "Jeremiah 44:10",
          "difficulty": "hard"
        },
        {
          "id": "jeremiah-44-hard-q11",
          "question": "The repeated references to burning incense to 'the queen of heaven' in Jeremiah 44 reveal what about the syncretism in Israelite religion at this time?",
          "type": "multiple-choice",
          "options": [
            "The Israelites incorporated foreign goddess worship into their practices",
            "They strictly adhered to Yahweh worship only",
            "They abandoned all religious practices",
            "They worshipped only the Babylonian gods"
          ],
          "correctAnswer": "The Israelites incorporated foreign goddess worship into their practices",
          "explanation": "Jeremiah 44:17 and following show the people worshipping the 'queen of heaven,' a foreign deity, alongside Yahweh, illustrating syncretism.",
          "verseReference": "Jeremiah 44:17",
          "difficulty": "hard"
        },
        {
          "id": "jeremiah-44-hard-q12",
          "question": "How does Jeremiah 44 illustrate the theme of covenant unfaithfulness found throughout the Hebrew Scriptures?",
          "type": "multiple-choice",
          "options": [
            "By showing Israel's worship of other gods despite prophetic warnings",
            "By recounting Israel's military victories",
            "By describing the building of the temple",
            "By establishing a new covenant with Egypt"
          ],
          "correctAnswer": "By showing Israel's worship of other gods despite prophetic warnings",
          "explanation": "The chapter documents Israel's idolatry and refusal to repent despite God's prophets, highlighting covenant unfaithfulness (Jeremiah 44:4-5).",
          "verseReference": "Jeremiah 44:4-5",
          "difficulty": "hard"
        },
        {
          "id": "jeremiah-44-hard-q13",
          "question": "Which literary device is prominently used in Jeremiah 44:8-9 where the LORD questions the people's actions and their forgetfulness of past sins?",
          "type": "multiple-choice",
          "options": [
            "Rhetorical questioning",
            "Chiasmus",
            "Parable",
            "Metaphor"
          ],
          "correctAnswer": "Rhetorical questioning",
          "explanation": "Verses 8-9 use rhetorical questions to challenge the people's memory and responsibility for their sins.",
          "verseReference": "Jeremiah 44:8-9",
          "difficulty": "hard"
        },
        {
          "id": "jeremiah-44-hard-q14",
          "question": "Jeremiah 44's mention of the cities Migdol, Tahpanhes, Noph, and Pathros situates the narrative in what historical-cultural context?",
          "type": "multiple-choice",
          "options": [
            "The Jewish exile community living in Egypt after Jerusalem's fall",
            "The original Promised Land",
            "Babylonian territory during the exile",
            "Philistine coastal cities"
          ],
          "correctAnswer": "The Jewish exile community living in Egypt after Jerusalem's fall",
          "explanation": "Jeremiah 44:1 lists these Egyptian locations where Jews had settled, reflecting the historical exile context.",
          "verseReference": "Jeremiah 44:1",
          "difficulty": "hard"
        },
        {
          "id": "jeremiah-44-hard-q15",
          "question": "What theological theme does the punishment of Pharaohhophra in Jeremiah 44:30 parallel from earlier in the book of Jeremiah?",
          "type": "multiple-choice",
          "options": [
            "The fate of Zedekiah as an example of divine judgment",
            "The promise of a messianic king",
            "The covenant blessings for obedience",
            "The establishment of a new temple"
          ],
          "correctAnswer": "The fate of Zedekiah as an example of divine judgment",
          "explanation": "Jeremiah 44:30 draws a parallel between Pharaohhophra’s fate and Zedekiah’s captivity, emphasizing God's judgment.",
          "verseReference": "Jeremiah 44:30",
          "difficulty": "hard"
        }
      ],
      "difficulty": "hard",
      "isBookQuiz": false,
      "slug": "jeremiah-44-quiz",
      "tags": [
        "jeremiah",
        "chapter-44",
        "jeremiah",
        "bible-quiz",
        "hard"
      ],
      "totalQuestions": 15,
      "estimatedTime": 15
    },
    "theological": {
      "id": "jeremiah-44-theological",
      "title": "Jeremiah Chapter 44 Quiz - Theological Level",
      "description": "Deep biblical theology from Jeremiah Chapter 44 that unites all believers. Explore foundational truths about God, creation, and humanity.",
      "type": "chapter",
      "book": "Jeremiah",
      "chapter": 44,
      "questions": [
        {
          "id": "jeremiah-44-theological-q1",
          "question": "According to Jeremiah 44, what was the primary reason God brought desolation upon Jerusalem and the cities of Judah?",
          "type": "multiple-choice",
          "options": [
            "Their wickedness and idolatry by serving other gods",
            "Their refusal to pay taxes",
            "Their lack of military strength",
            "Their neglect of the temple building"
          ],
          "correctAnswer": "Their wickedness and idolatry by serving other gods",
          "explanation": "Jeremiah 44:2-3 explains that the desolation was due to the wickedness of the people provoking God by burning incense and serving other gods, which parallels the consistent biblical theme that idolatry incurs God's judgment (Exodus 20:3-5; Deuteronomy 6:14-15; 1 Kings 11:4; Romans 1:21-23).",
          "verseReference": "Jeremiah 44:2-3",
          "difficulty": "hard"
        },
        {
          "id": "jeremiah-44-theological-q2",
          "question": "What did God repeatedly send to the people to warn them against idolatry, according to Jeremiah 44?",
          "type": "multiple-choice",
          "options": [
            "His servants the prophets",
            "Angelic messengers",
            "Mighty warriors",
            "Dreams and visions"
          ],
          "correctAnswer": "His servants the prophets",
          "explanation": "Jeremiah 44:4 states God sent his servants the prophets early and repeatedly to warn the people not to commit abominable acts, consistent with the biblical role of prophets as God’s messengers (Amos 3:7; 2 Chronicles 36:15; Hebrews 1:1; Acts 3:24).",
          "verseReference": "Jeremiah 44:4",
          "difficulty": "hard"
        },
        {
          "id": "jeremiah-44-theological-q3",
          "question": "In Jeremiah 44, what was the people's response to Jeremiah's warnings about burning incense to other gods?",
          "type": "multiple-choice",
          "options": [
            "They rejected Jeremiah's words and vowed to continue burning incense to the queen of heaven",
            "They repented and ceased idolatry",
            "They sought to return to Jerusalem immediately",
            "They ignored Jeremiah but stopped the incense"
          ],
          "correctAnswer": "They rejected Jeremiah's words and vowed to continue burning incense to the queen of heaven",
          "explanation": "Jeremiah 44:15-17 reveals the people's stubborn refusal to heed God's word, choosing instead to persist in idolatry, specifically worshiping the queen of heaven, illustrating human resistance to divine correction (Proverbs 1:24-26; Ezekiel 2:6; Hebrews 3:7-8; Revelation 2:14).",
          "verseReference": "Jeremiah 44:15-17",
          "difficulty": "hard"
        },
        {
          "id": "jeremiah-44-theological-q4",
          "question": "According to Jeremiah 44, what consequences did God declare would come upon the remnant of Judah living in Egypt?",
          "type": "multiple-choice",
          "options": [
            "They would be consumed by sword, famine, and become a curse and reproach",
            "They would prosper and multiply",
            "They would establish a new kingdom",
            "They would be protected and blessed"
          ],
          "correctAnswer": "They would be consumed by sword, famine, and become a curse and reproach",
          "explanation": "Jeremiah 44:12-13 clearly states that the remnant in Egypt would face destruction by sword and famine, becoming a curse and reproach, affirming God's righteous judgment on persistent sin (Leviticus 26:14-17; Deuteronomy 28:20-22; Ezekiel 5:16; Matthew 23:38).",
          "verseReference": "Jeremiah 44:12-13",
          "difficulty": "hard"
        },
        {
          "id": "jeremiah-44-theological-q5",
          "question": "What does Jeremiah 44 say about God's remembrance of the incense burned to other gods in Judah?",
          "type": "multiple-choice",
          "options": [
            "The LORD remembered and could no longer bear their evil deeds",
            "The LORD ignored it",
            "The LORD accepted it as a compromise",
            "The LORD blessed their offerings"
          ],
          "correctAnswer": "The LORD remembered and could no longer bear their evil deeds",
          "explanation": "Jeremiah 44:21-22 explains that God did remember the incense burned to other gods and could no longer bear their evil, resulting in desolation, consistent with God's holiness and intolerance of sin (Psalm 50:21; Isaiah 59:2; Hebrews 10:26-29; Revelation 2:20-23).",
          "verseReference": "Jeremiah 44:21-22",
          "difficulty": "hard"
        },
        {
          "id": "jeremiah-44-theological-q6",
          "question": "What was God's declaration regarding His name among the Judahites living in Egypt, as stated in Jeremiah 44?",
          "type": "multiple-choice",
          "options": [
            "His name shall no more be named in their mouths",
            "His name shall be exalted among them",
            "His name shall be their protector",
            "His name shall be a light to their path"
          ],
          "correctAnswer": "His name shall no more be named in their mouths",
          "explanation": "Jeremiah 44:26 reveals God's judgment that His name would no longer be invoked by the Judahites in Egypt, demonstrating the severity of their apostasy and divine judgment (Exodus 20:7; Leviticus 19:12; Malachi 1:14; Revelation 21:8).",
          "verseReference": "Jeremiah 44:26",
          "difficulty": "hard"
        },
        {
          "id": "jeremiah-44-theological-q7",
          "question": "How does Jeremiah 44 describe the fate of Pharaohhophra, king of Egypt?",
          "type": "multiple-choice",
          "options": [
            "He will be given into the hand of his enemies",
            "He will reign in peace and prosperity",
            "He will ally with Judah against Babylon",
            "He will build a temple for the LORD"
          ],
          "correctAnswer": "He will be given into the hand of his enemies",
          "explanation": "Jeremiah 44:30 prophesies the downfall of Pharaohhophra, comparing it to Zedekiah’s fate, emphasizing God's sovereign control over kings and kingdoms as part of His judgment (Daniel 4:17; Isaiah 10:5; Psalm 2:2-4; Acts 17:26).",
          "verseReference": "Jeremiah 44:30",
          "difficulty": "hard"
        },
        {
          "id": "jeremiah-44-theological-q8",
          "question": "What theological truth about divine justice is emphasized in Jeremiah 44 regarding God's punishment of sin?",
          "type": "multiple-choice",
          "options": [
            "God's judgment is certain and proportional to persistent disobedience",
            "God arbitrarily punishes without warning",
            "God punishes only the innocent",
            "God rewards sin for a time before punishing"
          ],
          "correctAnswer": "God's judgment is certain and proportional to persistent disobedience",
          "explanation": "Jeremiah 44 emphasizes that despite multiple warnings, persistent idolatry leads to certain judgment, highlighting God's justice and wrath against sin (Numbers 14:18; Romans 2:5-6; Ezekiel 18:20; Hebrews 10:26-31).",
          "verseReference": "Jeremiah 44:5-6, 11-13",
          "difficulty": "hard"
        },
        {
          "id": "jeremiah-44-theological-q9",
          "question": "What does the chapter teach about human stubbornness and repentance in the context of idolatry?",
          "type": "multiple-choice",
          "options": [
            "The people refused to humble themselves or turn from their sins despite warnings",
            "They immediately repented and returned to God",
            "They questioned Jeremiah and sought clarification",
            "They secretly repented but publicly denied it"
          ],
          "correctAnswer": "The people refused to humble themselves or turn from their sins despite warnings",
          "explanation": "Jeremiah 44:10 and 16 show the people's refusal to fear God or obey His law, stressing human obstinance against repentance (Proverbs 1:24-28; Isaiah 1:5-6; Hebrews 3:12-13; Luke 13:3).",
          "verseReference": "Jeremiah 44:10, 16",
          "difficulty": "hard"
        },
        {
          "id": "jeremiah-44-theological-q10",
          "question": "What does Jeremiah 44 reveal about the people's justification for continuing to worship the \"queen of heaven\"?",
          "type": "multiple-choice",
          "options": [
            "They claimed they prospered when they worshiped her and suffered when they ceased",
            "They said it was a new practice they wanted to try",
            "They admitted it was wrong but felt forced",
            "They blamed Jeremiah for their troubles"
          ],
          "correctAnswer": "They claimed they prospered when they worshiped her and suffered when they ceased",
          "explanation": "Jeremiah 44:17-18 states the people's rationale that burning incense to the queen of heaven brought them plenty and well-being, while stopping caused famine and sword, illustrating human misattribution of blessings apart from God (Deuteronomy 8:10-18; Jeremiah 2:11-13; James 1:17; 2 Corinthians 4:4).",
          "verseReference": "Jeremiah 44:17-18",
          "difficulty": "hard"
        },
        {
          "id": "jeremiah-44-theological-q11",
          "question": "What does Jeremiah 44 teach about the relationship between covenant obedience and national welfare?",
          "type": "multiple-choice",
          "options": [
            "Disobedience leads to desolation and curses, obedience leads to blessing",
            "Obedience has no effect on national fortunes",
            "National welfare depends solely on military strength",
            "Blessings come from sacrifices to any deity"
          ],
          "correctAnswer": "Disobedience leads to desolation and curses, obedience leads to blessing",
          "explanation": "Jeremiah 44:22-23 links the land’s desolation to covenant disobedience, consistent with the covenant theology principle that obedience to God brings blessing and disobedience brings curses (Deuteronomy 28; Leviticus 26; Psalm 89:30-37; Galatians 6:7-8).",
          "verseReference": "Jeremiah 44:22-23",
          "difficulty": "hard"
        },
        {
          "id": "jeremiah-44-theological-q12",
          "question": "What does Jeremiah 44 teach about the consequences of idolatry on future generations?",
          "type": "multiple-choice",
          "options": [
            "Idolatry results in cutting off man, woman, child, and suckling from the community",
            "Idolatry benefits future generations with prosperity",
            "Idolatry has no impact on descendants",
            "Idolatry is forgotten by God over time"
          ],
          "correctAnswer": "Idolatry results in cutting off man, woman, child, and suckling from the community",
          "explanation": "Jeremiah 44:7-8 warns that idolatry causes complete destruction of all people including children, affirming biblical teaching on the corporate consequences of sin (Exodus 20:5; 2 Kings 21:16; Ezekiel 9:6; Romans 1:18-32).",
          "verseReference": "Jeremiah 44:7-8",
          "difficulty": "hard"
        },
        {
          "id": "jeremiah-44-theological-q13",
          "question": "How does Jeremiah 44 portray God's sovereignty over historical events and rulers?",
          "type": "multiple-choice",
          "options": [
            "God controls the fate of kings and nations to fulfill His purposes",
            "Kings rule independently of God’s will",
            "God is unaware of political events",
            "Historical events happen by chance"
          ],
          "correctAnswer": "God controls the fate of kings and nations to fulfill His purposes",
          "explanation": "Verses like Jeremiah 44:30 show God handing Pharaohhophra to enemies, demonstrating divine sovereignty in history, consistent with biblical teaching on God’s control over rulers (Daniel 2:21; Proverbs 21:1; Isaiah 45:1; Romans 13:1).",
          "verseReference": "Jeremiah 44:30",
          "difficulty": "hard"
        },
        {
          "id": "jeremiah-44-theological-q14",
          "question": "What is the significance of the 'queen of heaven' in Jeremiah 44 in relation to biblical idolatry?",
          "type": "multiple-choice",
          "options": [
            "She represents a pagan goddess worshiped instead of Yahweh",
            "She is an angel sent by God",
            "She symbolizes the true God under a different name",
            "She is a prophetess among the people"
          ],
          "correctAnswer": "She represents a pagan goddess worshiped instead of Yahweh",
          "explanation": "The 'queen of heaven' mentioned in Jeremiah 44:17-19 refers to a pagan deity whom the people worshiped, illustrating the idolatry condemned throughout Scripture (Exodus 20:3; Judges 2:13; 1 Kings 11:5; Revelation 17:1-6).",
          "verseReference": "Jeremiah 44:17-19",
          "difficulty": "hard"
        },
        {
          "id": "jeremiah-44-theological-q15",
          "question": "What eschatological warning does Jeremiah 44 convey about the remnant that escapes judgment?",
          "type": "multiple-choice",
          "options": [
            "A small number will return to Judah to witness whose word stands",
            "All will perish without exception",
            "The remnant will establish a new eternal kingdom in Egypt",
            "The remnant will cease to exist"
          ],
          "correctAnswer": "A small number will return to Judah to witness whose word stands",
          "explanation": "Jeremiah 44:28 describes a remnant returning to Judah, highlighting the biblical motif of a faithful remnant that survives judgment, which is significant in eschatology and God's redemptive plan (Isaiah 10:20-22; Romans 11:5; Revelation 12:17; Zechariah 13:8).",
          "verseReference": "Jeremiah 44:28",
          "difficulty": "hard"
        }
      ],
      "difficulty": "hard",
      "isBookQuiz": false,
      "slug": "jeremiah-44-quiz",
      "tags": [
        "jeremiah",
        "chapter-44",
        "jeremiah",
        "bible-quiz",
        "theological"
      ],
      "totalQuestions": 15,
      "estimatedTime": 25
    }
  }
}