{
  "id": "numbers-15-tabbed",
  "title": "Numbers Chapter 15 Quiz - Multi-Level",
  "description": "An enhanced quiz on Numbers chapter 15 with Easy, Medium, Hard, and Theological levels. Each level has 15 carefully crafted questions. Choose your difficulty and dive in!",
  "tabs": {
    "easy": {
      "id": "numbers-15-easy",
      "title": "Numbers Chapter 15 Quiz - Easy Level",
      "description": "Perfect for beginners! Test your basic knowledge of Numbers Chapter 15.",
      "type": "chapter",
      "book": "Numbers",
      "chapter": 15,
      "questions": [
        {
          "id": "numbers-15-easy-q1",
          "question": "According to Numbers 15:3, what types of offerings did the LORD say to make by fire?",
          "type": "multiple-choice",
          "options": [
            "Burnt offering, sacrifice for a vow, freewill offering, and solemn feasts",
            "Only burnt offerings",
            "Sin offerings and guilt offerings",
            "Peace offerings and thank offerings"
          ],
          "correctAnswer": "Burnt offering, sacrifice for a vow, freewill offering, and solemn feasts",
          "explanation": "Numbers 15:3 states the LORD instructed offerings by fire to include burnt offerings, sacrifices in performing a vow, freewill offerings, and solemn feasts.",
          "verseReference": "Numbers 15:3",
          "difficulty": "easy"
        },
        {
          "id": "numbers-15-easy-q2",
          "question": "What amount of flour was to be mingled with oil for a meat offering when offering one lamb according to Numbers 15:4?",
          "type": "multiple-choice",
          "options": [
            "A tenth deal of flour",
            "Two tenth deals of flour",
            "Three tenth deals of flour",
            "Half a deal of flour"
          ],
          "correctAnswer": "A tenth deal of flour",
          "explanation": "Numbers 15:4 specifies a meat offering of a tenth deal of flour mingled with oil for one lamb offering.",
          "verseReference": "Numbers 15:4",
          "difficulty": "easy"
        },
        {
          "id": "numbers-15-easy-q3",
          "question": "For a ram, how much wine was to be offered as a drink offering according to Numbers 15:7?",
          "type": "multiple-choice",
          "options": [
            "The third part of an hin",
            "The fourth part of an hin",
            "Half an hin",
            "One hin"
          ],
          "correctAnswer": "The third part of an hin",
          "explanation": "Numbers 15:7 directs that for a ram, a drink offering of the third part of an hin of wine is prepared.",
          "verseReference": "Numbers 15:7",
          "difficulty": "easy"
        },
        {
          "id": "numbers-15-easy-q4",
          "question": "What is the meat offering quantity mixed with oil for a burnt offering of a bullock as stated in Numbers 15:9?",
          "type": "multiple-choice",
          "options": [
            "Three tenth deals of flour mingled with half an hin of oil",
            "Two tenth deals of flour mingled with a third part of an hin of oil",
            "A tenth deal of flour mingled with a fourth part of an hin of oil",
            "Five tenth deals of flour mingled with one hin of oil"
          ],
          "correctAnswer": "Three tenth deals of flour mingled with half an hin of oil",
          "explanation": "Numbers 15:9 says a bullock offering requires three tenth deals of flour mingled with half an hin of oil as the meat offering.",
          "verseReference": "Numbers 15:9",
          "difficulty": "easy"
        },
        {
          "id": "numbers-15-easy-q5",
          "question": "According to Numbers 15:11, the instructions for burnt offerings apply to which animals?",
          "type": "multiple-choice",
          "options": [
            "Bullock, ram, lamb, or kid",
            "Only bullocks",
            "Only lambs and kids",
            "Ram and bullock only"
          ],
          "correctAnswer": "Bullock, ram, lamb, or kid",
          "explanation": "Numbers 15:11 clarifies that the same offerings apply for bullock, ram, lamb, or kid.",
          "verseReference": "Numbers 15:11",
          "difficulty": "easy"
        },
        {
          "id": "numbers-15-easy-q6",
          "question": "Who must follow the same ordinance in offering to the LORD, as stated in Numbers 15:15?",
          "type": "multiple-choice",
          "options": [
            "The congregation and the stranger sojourning among them",
            "Only the children of Israel",
            "Only the priests",
            "Only the strangers"
          ],
          "correctAnswer": "The congregation and the stranger sojourning among them",
          "explanation": "Numbers 15:15 states the ordinance is for both the congregation and the stranger sojourning among them.",
          "verseReference": "Numbers 15:15",
          "difficulty": "easy"
        },
        {
          "id": "numbers-15-easy-q7",
          "question": "What shall the children of Israel offer when they eat bread of the land, according to Numbers 15:19?",
          "type": "multiple-choice",
          "options": [
            "An heave offering unto the LORD",
            "A burnt offering",
            "A sin offering",
            "No offering is required"
          ],
          "correctAnswer": "An heave offering unto the LORD",
          "explanation": "Numbers 15:19 commands offering an heave offering when eating bread of the land.",
          "verseReference": "Numbers 15:19",
          "difficulty": "easy"
        },
        {
          "id": "numbers-15-easy-q8",
          "question": "What is the consequence for one who sins presumptuously, according to Numbers 15:30?",
          "type": "multiple-choice",
          "options": [
            "That soul shall be cut off from among his people",
            "They shall offer a sin offering",
            "They shall be forgiven after prayer",
            "They shall bring a young bullock offering"
          ],
          "correctAnswer": "That soul shall be cut off from among his people",
          "explanation": "Numbers 15:30 states that a presumptuous sinner is cut off from among his people.",
          "verseReference": "Numbers 15:30",
          "difficulty": "easy"
        },
        {
          "id": "numbers-15-easy-q9",
          "question": "Who was found gathering sticks on the sabbath day according to Numbers 15:32?",
          "type": "multiple-choice",
          "options": [
            "A man among the children of Israel",
            "A Levite priest",
            "Moses himself",
            "A stranger sojourning"
          ],
          "correctAnswer": "A man among the children of Israel",
          "explanation": "Numbers 15:32 records that the children of Israel found a man gathering sticks on the sabbath.",
          "verseReference": "Numbers 15:32",
          "difficulty": "easy"
        },
        {
          "id": "numbers-15-easy-q10",
          "question": "What was the punishment for the man found gathering sticks on the sabbath according to Numbers 15:35?",
          "type": "multiple-choice",
          "options": [
            "He shall be put to death by stoning without the camp",
            "He was forgiven after prayer",
            "He was fined",
            "He was made to rest for a day"
          ],
          "correctAnswer": "He shall be put to death by stoning without the camp",
          "explanation": "Numbers 15:35 commands that the man be stoned to death outside the camp.",
          "verseReference": "Numbers 15:35",
          "difficulty": "easy"
        },
        {
          "id": "numbers-15-easy-q11",
          "question": "What did the LORD command the children of Israel to make on the borders of their garments, as stated in Numbers 15:38?",
          "type": "multiple-choice",
          "options": [
            "Fringes with a ribband of blue",
            "Golden threads",
            "Silver bells",
            "Tassels of white"
          ],
          "correctAnswer": "Fringes with a ribband of blue",
          "explanation": "Numbers 15:38 instructs making fringes on garment borders with a blue ribband.",
          "verseReference": "Numbers 15:38",
          "difficulty": "easy"
        },
        {
          "id": "numbers-15-easy-q12",
          "question": "True or False: Numbers 15:16 says there should be different laws for the stranger and the children of Israel.",
          "type": "true-false",
          "options": [
            "True",
            "False"
          ],
          "correctAnswer": "False",
          "explanation": "Numbers 15:16 states there shall be one law and one manner for both the children of Israel and the stranger.",
          "verseReference": "Numbers 15:16",
          "difficulty": "easy"
        },
        {
          "id": "numbers-15-easy-q13",
          "question": "True or False: According to Numbers 15:26, the congregation and the stranger will be forgiven if they sinned in ignorance.",
          "type": "true-false",
          "options": [
            "True",
            "False"
          ],
          "correctAnswer": "True",
          "explanation": "Numbers 15:26 says all the congregation and the stranger shall be forgiven because the sin was in ignorance.",
          "verseReference": "Numbers 15:26",
          "difficulty": "easy"
        },
        {
          "id": "numbers-15-easy-q14",
          "question": "True or False: Numbers 15:39 says the fringes on garments are to remind the people to follow their own hearts and eyes.",
          "type": "true-false",
          "options": [
            "True",
            "False"
          ],
          "correctAnswer": "False",
          "explanation": "Numbers 15:39 says the fringes are to remind them to obey God's commandments and not follow their own hearts and eyes.",
          "verseReference": "Numbers 15:39",
          "difficulty": "easy"
        },
        {
          "id": "numbers-15-easy-q15",
          "question": "Complete the verse from Numbers 15:21: 'Of the first of your dough ye shall give unto the LORD an _______ in your generations.'",
          "type": "fill-blank",
          "options": [
            "heave offering",
            "burnt offering",
            "sin offering",
            "peace offering"
          ],
          "correctAnswer": "heave offering",
          "explanation": "Numbers 15:21 commands giving the first of the dough as a heave offering unto the LORD.",
          "verseReference": "Numbers 15:21",
          "difficulty": "easy"
        }
      ],
      "difficulty": "easy",
      "isBookQuiz": false,
      "slug": "numbers-15-quiz",
      "tags": [
        "numbers",
        "chapter-15",
        "numbers",
        "bible-quiz",
        "easy"
      ],
      "totalQuestions": 15,
      "estimatedTime": 8
    },
    "medium": {
      "id": "numbers-15-medium",
      "title": "Numbers Chapter 15 Quiz - Medium Level",
      "description": "Ready for more? Apply biblical truths from Numbers Chapter 15 to real-life situations.",
      "type": "chapter",
      "book": "Numbers",
      "chapter": 15,
      "questions": [
        {
          "id": "numbers-15-medium-q1",
          "question": "A fellow believer is confused about how to properly offer sacrifices according to God's command. Based on Numbers 15:3-11, what principle about offerings would you share to encourage obedience and reverence in worship?",
          "type": "multiple-choice",
          "options": [
            "Offerings must include specific amounts of flour, oil, and wine according to the animal sacrificed",
            "Offerings can be made in any quantity one chooses",
            "Only burnt offerings are acceptable to the LORD",
            "Offerings should be made only during festivals"
          ],
          "correctAnswer": "Offerings must include specific amounts of flour, oil, and wine according to the animal sacrificed",
          "explanation": "Numbers 15:3-11 details that the LORD commanded exact portions of flour, oil, and wine to accompany burnt offerings or sacrifices, emphasizing obedience and reverence in worship. This shows the importance of following God's instructions precisely in offerings.",
          "verseReference": "Numbers 15:3-11",
          "difficulty": "medium"
        },
        {
          "id": "numbers-15-medium-q2",
          "question": "How does Numbers 15:14-16 teach us about the inclusion of strangers or foreigners in the community of faith?",
          "type": "multiple-choice",
          "options": [
            "Strangers must follow different laws than native-born Israelites",
            "Strangers who sojourn with you must follow the same laws and ordinances as the congregation",
            "Strangers are exempt from offerings and sacrifices",
            "Strangers can only participate in feasts but not in sacrifices"
          ],
          "correctAnswer": "Strangers who sojourn with you must follow the same laws and ordinances as the congregation",
          "explanation": "Numbers 15:14-16 explains that one ordinance applies both to the congregation and to the stranger sojourning among them, teaching us inclusiveness and equal accountability before God, promoting unity in the community of faith.",
          "verseReference": "Numbers 15:14-16",
          "difficulty": "medium"
        },
        {
          "id": "numbers-15-medium-q3",
          "question": "A believer struggles with feeling unworthy after sinning unknowingly. Based on Numbers 15:22-29, what biblical truth would you share about God's forgiveness in cases of unintentional sin?",
          "type": "multiple-choice",
          "options": [
            "God requires a sin offering and the priest will make atonement, forgiving the person",
            "God does not forgive sins committed unknowingly",
            "Only the elders can forgive unintentional sins",
            "Unintentional sins must be confessed publicly without offering"
          ],
          "correctAnswer": "God requires a sin offering and the priest will make atonement, forgiving the person",
          "explanation": "Numbers 15:22-29 outlines that if anyone sins through ignorance, they must bring a sin offering, and the priest will make atonement, resulting in forgiveness. This teaches God's grace and provision for unintentional faults.",
          "verseReference": "Numbers 15:22-29",
          "difficulty": "medium"
        },
        {
          "id": "numbers-15-medium-q4",
          "question": "What does Numbers 15:30-31 warn about attitudes toward God's commandments and their consequences?",
          "type": "multiple-choice",
          "options": [
            "Presumptuous sin, or intentional rebellion, leads to being cut off from the people",
            "God overlooks all sins if confessed",
            "Only strangers are punished for breaking commandments",
            "Sinning intentionally has no serious consequences"
          ],
          "correctAnswer": "Presumptuous sin, or intentional rebellion, leads to being cut off from the people",
          "explanation": "Numbers 15:30-31 warns that a soul who sins presumptuously despises the LORD's word and will be cut off from the people, highlighting the seriousness of deliberate disobedience.",
          "verseReference": "Numbers 15:30-31",
          "difficulty": "medium"
        },
        {
          "id": "numbers-15-medium-q5",
          "question": "A believer asks about the importance of remembering God's commandments daily. Based on Numbers 15:38-40, what practical spiritual discipline would you recommend?",
          "type": "multiple-choice",
          "options": [
            "Wearing fringes with a blue ribbon on garments as a reminder to obey God's commandments",
            "Reciting the law only during festivals",
            "Ignoring outward signs and focusing only on inner feelings",
            "Keeping commandments only when in the temple"
          ],
          "correctAnswer": "Wearing fringes with a blue ribbon on garments as a reminder to obey God's commandments",
          "explanation": "Numbers 15:38-40 commands the Israelites to make fringes on their garments with a blue ribbon to remind them to obey all God's commandments, emphasizing practical measures to maintain spiritual discipline and holiness.",
          "verseReference": "Numbers 15:38-40",
          "difficulty": "medium"
        },
        {
          "id": "numbers-15-medium-q6",
          "question": "True or False: According to Numbers 15:24-26, when the congregation sins unknowingly, they must offer a young bullock for a burnt offering and a kid for a sin offering, and the priest will make atonement for them.",
          "type": "true-false",
          "options": [
            "True",
            "False"
          ],
          "correctAnswer": "True",
          "explanation": "Numbers 15:24-26 explains that if the congregation sins unknowingly, they must bring specific offerings and the priest will make atonement, resulting in forgiveness for the entire congregation.",
          "verseReference": "Numbers 15:24-26",
          "difficulty": "medium"
        },
        {
          "id": "numbers-15-medium-q7",
          "question": "How does Numbers 15:19-21 instruct the Israelites to honor God with the first portion of their food, and what virtue does this teach?",
          "type": "multiple-choice",
          "options": [
            "Offer a heave offering of the first dough to God as an act of faith and gratitude",
            "Keep all the first fruits for themselves",
            "Give the first fruits only after the harvest is complete",
            "Sacrifice animals instead of food offerings"
          ],
          "correctAnswer": "Offer a heave offering of the first dough to God as an act of faith and gratitude",
          "explanation": "Numbers 15:19-21 instructs offering a cake of the first dough as a heave offering, teaching faith, gratitude, and stewardship by dedicating the first of their produce to God.",
          "verseReference": "Numbers 15:19-21",
          "difficulty": "medium"
        },
        {
          "id": "numbers-15-medium-q8",
          "question": "A believer is struggling with temptation to disregard God's commands. Based on Numbers 15:39-40, what counsel would you give about remembering and obeying God's commandments?",
          "type": "multiple-choice",
          "options": [
            "Keep visible reminders to help you stay faithful and avoid following your own desires",
            "Rely solely on feelings to guide your actions",
            "Ignore commandments when they seem difficult",
            "Obey only when others are watching"
          ],
          "correctAnswer": "Keep visible reminders to help you stay faithful and avoid following your own desires",
          "explanation": "Numbers 15:39-40 encourages using fringes as reminders to remember God's commandments, resist personal desires, and be holy, teaching practical ways to persevere through temptation.",
          "verseReference": "Numbers 15:39-40",
          "difficulty": "medium"
        },
        {
          "id": "numbers-15-medium-q9",
          "question": "True or False: According to Numbers 15:32-36, a man who gathered sticks on the Sabbath was put to death by stoning as commanded by the LORD.",
          "type": "true-false",
          "options": [
            "True",
            "False"
          ],
          "correctAnswer": "True",
          "explanation": "Numbers 15:32-36 records that a man found gathering sticks on the Sabbath was put to death by stoning following the LORD's command, demonstrating the seriousness of honoring God's holy day.",
          "verseReference": "Numbers 15:32-36",
          "difficulty": "medium"
        },
        {
          "id": "numbers-15-medium-q10",
          "question": "How does Numbers 15:2-3 teach about offering sacrifices as an expression of faith and worship when entering God's promised land?",
          "type": "multiple-choice",
          "options": [
            "Offerings by fire, such as burnt offerings and sacrifices, are to be made to the LORD as acts of worship and dedication",
            "Sacrifices are optional and not connected to faith",
            "Only freewill offerings are acceptable to God",
            "Offerings should be made only in the wilderness"
          ],
          "correctAnswer": "Offerings by fire, such as burnt offerings and sacrifices, are to be made to the LORD as acts of worship and dedication",
          "explanation": "Numbers 15:2-3 instructs the Israelites to offer burnt offerings or sacrifices by fire to the LORD when they enter the land, showing worship and faith through obedience and dedication.",
          "verseReference": "Numbers 15:2-3",
          "difficulty": "medium"
        },
        {
          "id": "numbers-15-medium-q11",
          "question": "A fellow believer wonders how to maintain integrity in worship and community life. Based on Numbers 15:12-13, what teaching would you share about consistency in following God's commands?",
          "type": "multiple-choice",
          "options": [
            "Everyone born in the land must follow the same manner of offerings and worship consistently",
            "Only leaders are required to keep the offerings",
            "Offerings can vary according to personal preference",
            "Strangers are not required to follow worship customs"
          ],
          "correctAnswer": "Everyone born in the land must follow the same manner of offerings and worship consistently",
          "explanation": "Numbers 15:12-13 emphasizes that all who are born in the country must perform offerings in a consistent manner, teaching integrity and uniformity in worship and community life.",
          "verseReference": "Numbers 15:12-13",
          "difficulty": "medium"
        },
        {
          "id": "numbers-15-medium-q12",
          "question": "Fill in the blank: Numbers 15:4 instructs that with the burnt offering or sacrifice of one lamb, the meat offering should be a tenth deal of ______ mingled with the fourth part of an hin of oil.",
          "type": "fill-in-the-blank",
          "options": [
            "flour",
            "wine",
            "oil",
            "bread"
          ],
          "correctAnswer": "flour",
          "explanation": "Numbers 15:4 states that the meat offering accompanying the burnt offering should be a tenth deal of flour mixed with oil, instructing precise offerings as an act of obedience and devotion.",
          "verseReference": "Numbers 15:4",
          "difficulty": "medium"
        },
        {
          "id": "numbers-15-medium-q13",
          "question": "How does the command in Numbers 15:41 about God's identity encourage humility and gratitude in believers?",
          "type": "multiple-choice",
          "options": [
            "Recognizing God as the one who brought them out of Egypt reminds believers of His grace and sovereignty",
            "It commands believers to rely on their own strength",
            "It emphasizes earthly kings over God",
            "It focuses on wealth and possessions"
          ],
          "correctAnswer": "Recognizing God as the one who brought them out of Egypt reminds believers of His grace and sovereignty",
          "explanation": "Numbers 15:41 identifies the LORD as their God who delivered them from Egypt, encouraging humility, trust, and gratitude for His saving power and provision.",
          "verseReference": "Numbers 15:41",
          "difficulty": "medium"
        },
        {
          "id": "numbers-15-medium-q14",
          "question": "A believer wants to understand how to persevere through trials and maintain obedience. Based on Numbers 15:22-23, what principle about God's commandments would you share?",
          "type": "multiple-choice",
          "options": [
            "God's commandments are to be observed continually throughout all generations",
            "Commandments apply only to the first generation",
            "Commandments can be ignored if convenient",
            "Only priests must observe all commandments"
          ],
          "correctAnswer": "God's commandments are to be observed continually throughout all generations",
          "explanation": "Numbers 15:22-23 stresses that God's commandments given through Moses are to be observed forever among all generations, teaching perseverance and steadfastness in obedience.",
          "verseReference": "Numbers 15:22-23",
          "difficulty": "medium"
        }
      ],
      "difficulty": "medium",
      "isBookQuiz": false,
      "slug": "numbers-15-quiz",
      "tags": [
        "numbers",
        "chapter-15",
        "numbers",
        "bible-quiz",
        "medium"
      ],
      "totalQuestions": 14,
      "estimatedTime": 12
    },
    "hard": {
      "id": "numbers-15-hard",
      "title": "Numbers Chapter 15 Quiz - Hard Level",
      "description": "Challenge yourself with deep analysis and cross-biblical connections from Numbers Chapter 15.",
      "type": "chapter",
      "book": "Numbers",
      "chapter": 15,
      "questions": [
        {
          "id": "numbers-15-hard-q1",
          "question": "According to Numbers 15:2-10, which of the following best describes the composition of the meat offering accompanying a burnt offering of a ram?",
          "type": "multiple-choice",
          "options": [
            "Two tenth deals of flour mingled with the third part of an hin of oil",
            "A tenth deal of flour mingled with the fourth part of an hin of oil",
            "Three tenth deals of flour mingled with half an hin of oil",
            "One tenth deal of flour mingled with half an hin of oil"
          ],
          "correctAnswer": "Two tenth deals of flour mingled with the third part of an hin of oil",
          "explanation": "Numbers 15:6 specifies that for a ram, the meat offering should be two tenth deals of flour mingled with the third part of an hin of oil.",
          "verseReference": "Numbers 15:6",
          "difficulty": "hard"
        },
        {
          "id": "numbers-15-hard-q2",
          "question": "What is the significance of the 'one law and one manner' mentioned in Numbers 15:16 in the context of ancient Israelite society?",
          "type": "multiple-choice",
          "options": [
            "It establishes equality between native Israelites and resident strangers in religious observance",
            "It differentiates native Israelites from foreigners in legal matters",
            "It introduces a new covenant exclusive to the Levites",
            "It mandates separate offerings for Israelites and strangers"
          ],
          "correctAnswer": "It establishes equality between native Israelites and resident strangers in religious observance",
          "explanation": "Numbers 15:16 emphasizes that both Israelites and strangers sojourning among them must observe the same laws and manners, reflecting inclusivity and unity under God's covenant.",
          "verseReference": "Numbers 15:16",
          "difficulty": "hard"
        },
        {
          "id": "numbers-15-hard-q3",
          "question": "In Numbers 15:19-21, what type of offering is required when the Israelites eat the bread of the land, and how is it described?",
          "type": "multiple-choice",
          "options": [
            "A heave offering of a cake made from the first dough",
            "A burnt offering of a young bullock",
            "A sin offering of a kid goat",
            "A peace offering from the herd"
          ],
          "correctAnswer": "A heave offering of a cake made from the first dough",
          "explanation": "Numbers 15:19-20 commands that when eating the bread of the land, the Israelites must offer a heave offering made from the first of their dough, symbolizing dedication of the first fruits to God.",
          "verseReference": "Numbers 15:19-20",
          "difficulty": "hard"
        },
        {
          "id": "numbers-15-hard-q4",
          "question": "According to Numbers 15:22-31, how are sins committed through ignorance treated compared to presumptuous sins?",
          "type": "multiple-choice",
          "options": [
            "Ignorant sins can be atoned for with offerings; presumptuous sins result in being cut off",
            "Both ignorant and presumptuous sins require the same sin offering",
            "Presumptuous sins are forgiven without offering; ignorant sins require sacrifice",
            "Neither ignorant nor presumptuous sins require any offering"
          ],
          "correctAnswer": "Ignorant sins can be atoned for with offerings; presumptuous sins result in being cut off",
          "explanation": "The chapter contrasts sins done unknowingly, which can be atoned for by offerings (verses 24-28), with deliberate sins, which lead to being cut off from the people (verses 30-31).",
          "verseReference": "Numbers 15:24-31",
          "difficulty": "hard"
        },
        {
          "id": "numbers-15-hard-q5",
          "question": "The punishment for gathering sticks on the Sabbath in Numbers 15:32-36 reflects which broader biblical principle?",
          "type": "multiple-choice",
          "options": [
            "The sanctity of the Sabbath as a sign of covenantal faithfulness",
            "The importance of agricultural productivity",
            "The need for ritual purity before offerings",
            "The priority of communal work over individual needs"
          ],
          "correctAnswer": "The sanctity of the Sabbath as a sign of covenantal faithfulness",
          "explanation": "The severe punishment for violating the Sabbath by gathering sticks (verse 35) underscores the Sabbath's sacredness as a covenantal sign, later echoed in Exodus 31:16-17.",
          "verseReference": "Numbers 15:32-36",
          "difficulty": "hard"
        },
        {
          "id": "numbers-15-hard-q6",
          "question": "In Numbers 15:38-40, what is the purpose of the blue ribband attached to the fringes on the garments according to the text?",
          "type": "multiple-choice",
          "options": [
            "To remind the Israelites to keep all the commandments and be holy to God",
            "To denote the tribe of Levi exclusively",
            "To serve as a mark of the priesthood only",
            "To symbolize the waters of the Red Sea"
          ],
          "correctAnswer": "To remind the Israelites to keep all the commandments and be holy to God",
          "explanation": "Numbers 15:39-40 explains that the blue ribband on the fringes serves as a visual reminder to remember God's commandments and live a holy life.",
          "verseReference": "Numbers 15:38-40",
          "difficulty": "hard"
        },
        {
          "id": "numbers-15-hard-q7",
          "question": "The repeated instruction to offer a 'sweet savour unto the LORD' in Numbers 15 highlights what theological theme commonly found in Levitical laws?",
          "type": "multiple-choice",
          "options": [
            "The importance of offerings as acts of worship pleasing to God",
            "The necessity of animal sacrifice for forgiveness alone",
            "The exclusivity of Israel's worship over other nations",
            "The role of the temple priests as mediators"
          ],
          "correctAnswer": "The importance of offerings as acts of worship pleasing to God",
          "explanation": "The phrase 'sweet savour unto the LORD' (e.g., Numbers 15:3, 10) indicates that offerings are designed to be pleasing worship acts, symbolizing devotion and atonement.",
          "verseReference": "Numbers 15:3",
          "difficulty": "hard"
        },
        {
          "id": "numbers-15-hard-q8",
          "question": "Which aspect of Numbers 15 serves as a typological foreshadowing of Christ's atoning sacrifice in the New Testament?",
          "type": "multiple-choice",
          "options": [
            "The sin offering made by fire for unintentional sins",
            "The blue ribband on tassels",
            "The heave offering of the first dough",
            "The stoning of the man gathering sticks"
          ],
          "correctAnswer": "The sin offering made by fire for unintentional sins",
          "explanation": "The sin offering for inadvertent sins (Numbers 15:27-28) foreshadows Christ’s atoning sacrifice for humanity’s sins, as elaborated in Hebrews 9:22-28.",
          "verseReference": "Numbers 15:27-28",
          "difficulty": "hard"
        },
        {
          "id": "numbers-15-hard-q9",
          "question": "True or False: According to Numbers 15:14-15, strangers sojourning among Israel were exempt from observing the same ordinances as the native Israelites.",
          "type": "true-false",
          "options": [
            "True",
            "False"
          ],
          "correctAnswer": "False",
          "explanation": "Numbers 15:14-15 clearly states that strangers must observe the same ordinances as the native congregation, signifying inclusiveness in covenant obligations.",
          "verseReference": "Numbers 15:14-15",
          "difficulty": "hard"
        },
        {
          "id": "numbers-15-hard-q10",
          "question": "In the historical and cultural context of the ancient Near East, what does the detailed specification of offerings in Numbers 15:4-10 suggest about Israelite worship?",
          "type": "multiple-choice",
          "options": [
            "A structured and codified system emphasizing order and holiness",
            "A flexible approach allowing individual interpretation",
            "A minimal focus on sacrificial rituals",
            "A primarily symbolic rather than literal practice"
          ],
          "correctAnswer": "A structured and codified system emphasizing order and holiness",
          "explanation": "The precise measurements and offerings (Numbers 15:4-10) reflect the Israelite emphasis on orderly, holy worship distinct from neighboring cultures.",
          "verseReference": "Numbers 15:4-10",
          "difficulty": "hard"
        },
        {
          "id": "numbers-15-hard-q11",
          "question": "How does the punishment of the man gathering sticks on the Sabbath (Numbers 15:32-36) illustrate the concept of communal responsibility in Israelite law?",
          "type": "multiple-choice",
          "options": [
            "All the congregation participated in his execution, showing collective accountability",
            "Only the priests judged him, isolating responsibility",
            "He was forgiven without punishment to protect communal unity",
            "The elders alone decided his fate without the people"
          ],
          "correctAnswer": "All the congregation participated in his execution, showing collective accountability",
          "explanation": "Verse 36 explains that the entire congregation stoned the man, demonstrating collective responsibility for upholding the law.",
          "verseReference": "Numbers 15:36",
          "difficulty": "hard"
        },
        {
          "id": "numbers-15-hard-q12",
          "question": "What literary structure can be observed in the way Numbers 15 addresses offerings, commandments, and the fringes on garments?",
          "type": "multiple-choice",
          "options": [
            "A chiastic structure emphasizing obedience and remembrance",
            "A linear narrative without thematic repetition",
            "A prophetic oracle style",
            "A parabolic teaching format"
          ],
          "correctAnswer": "A chiastic structure emphasizing obedience and remembrance",
          "explanation": "The chapter moves from offerings to laws about ignorance and punishment, then to reminders through fringes, forming a chiastic pattern focusing on obedience and memory of God's commandments.",
          "verseReference": "Numbers 15:1-41",
          "difficulty": "hard"
        },
        {
          "id": "numbers-15-hard-q13",
          "question": "The instruction to 'remember all the commandments of the LORD' by looking at the blue fringe (Numbers 15:39) employs which literary device?",
          "type": "multiple-choice",
          "options": [
            "Visual symbolism as a mnemonic device",
            "Metaphor for divine protection",
            "Allegory of Israel's history",
            "Hyperbole emphasizing holiness"
          ],
          "correctAnswer": "Visual symbolism as a mnemonic device",
          "explanation": "The blue fringe acts as a visual reminder (Numbers 15:39), a symbol that helps Israelites remember and obey God's laws, using symbolism as a memory aid.",
          "verseReference": "Numbers 15:39",
          "difficulty": "hard"
        },
        {
          "id": "numbers-15-hard-q14",
          "question": "According to Numbers 15:30-31, what is the consequence for one who sins presumptuously, and how does it reflect the nature of the offense?",
          "type": "multiple-choice",
          "options": [
            "They shall be cut off because they despise the word of the LORD",
            "They must offer a sin offering and are forgiven",
            "They receive a warning but no punishment",
            "They are required to fast for seven days"
          ],
          "correctAnswer": "They shall be cut off because they despise the word of the LORD",
          "explanation": "Verses 30-31 state that presumptuous sinners who despise God's word are cut off, showing the severity of willful disobedience.",
          "verseReference": "Numbers 15:30-31",
          "difficulty": "hard"
        },
        {
          "id": "numbers-15-hard-q15",
          "question": "Fill in the blank: Numbers 15:41 declares, 'I am the LORD your God, which brought you out of the land of ________, to be your God.'",
          "type": "multiple-choice",
          "options": [
            "Egypt",
            "Babylon",
            "Canaan",
            "Assyria"
          ],
          "correctAnswer": "Egypt",
          "explanation": "Verse 41 refers to God bringing Israel out of Egypt, a foundational event for their identity and covenant relationship.",
          "verseReference": "Numbers 15:41",
          "difficulty": "hard"
        }
      ],
      "difficulty": "hard",
      "isBookQuiz": false,
      "slug": "numbers-15-quiz",
      "tags": [
        "numbers",
        "chapter-15",
        "numbers",
        "bible-quiz",
        "hard"
      ],
      "totalQuestions": 15,
      "estimatedTime": 15
    },
    "theological": {
      "id": "numbers-15-theological",
      "title": "Numbers Chapter 15 Quiz - Theological Level",
      "description": "Deep biblical theology from Numbers Chapter 15 that unites all believers. Explore foundational truths about God, creation, and humanity.",
      "type": "chapter",
      "book": "Numbers",
      "chapter": 15,
      "questions": [
        {
          "id": "numbers-15-theological-q1",
          "question": "According to Numbers 15, what is the purpose of the offerings made by fire to the LORD?",
          "type": "multiple-choice",
          "options": [
            "To make a sweet savour unto the LORD",
            "To gain political power",
            "To earn material wealth",
            "To establish man-made traditions"
          ],
          "correctAnswer": "To make a sweet savour unto the LORD",
          "explanation": "Numbers 15:3 states that offerings by fire are made 'to make a sweet savour unto the LORD.' This reflects God's desire for worship through sacrifice, consistent with Leviticus 1:9 and Hebrews 13:15 where offerings are pleasing to God. It emphasizes the worshipful nature of sacrifices rather than worldly gains.",
          "verseReference": "Numbers 15:3",
          "difficulty": "hard"
        },
        {
          "id": "numbers-15-theological-q2",
          "question": "What quantity of flour is mixed with oil for a meat offering accompanying a lamb burnt offering?",
          "type": "multiple-choice",
          "options": [
            "A tenth deal of flour",
            "Two tenth deals of flour",
            "Three tenth deals of flour",
            "One deal of flour"
          ],
          "correctAnswer": "A tenth deal of flour",
          "explanation": "Numbers 15:4 specifies that the meat offering accompanying a lamb is a tenth deal of flour mixed with oil. This precise measurement underscores the detailed regulations God gave for worship, showing His holiness and order (Exodus 29:40, Leviticus 2:1).",
          "verseReference": "Numbers 15:4",
          "difficulty": "hard"
        },
        {
          "id": "numbers-15-theological-q3",
          "question": "In Numbers 15, how is the law described for the native-born Israelites and the strangers living among them?",
          "type": "multiple-choice",
          "options": [
            "One law and one manner shall be for both",
            "Different laws for natives and strangers",
            "Strangers are exempt from laws",
            "Only natives must obey the law"
          ],
          "correctAnswer": "One law and one manner shall be for both",
          "explanation": "Numbers 15:16 stresses that 'One law and one manner shall be for you, and for the stranger that sojourneth with you,' highlighting God's impartial justice and universal application of His commands (Leviticus 24:22, Deuteronomy 1:16, Acts 10:34).",
          "verseReference": "Numbers 15:16",
          "difficulty": "hard"
        },
        {
          "id": "numbers-15-theological-q4",
          "question": "What offering must be brought if the whole congregation sins through ignorance according to Numbers 15?",
          "type": "multiple-choice",
          "options": [
            "One young bullock for a burnt offering and one kid for a sin offering",
            "Only a sin offering goat",
            "A burnt offering of a lamb",
            "No offering is required"
          ],
          "correctAnswer": "One young bullock for a burnt offering and one kid for a sin offering",
          "explanation": "Numbers 15:24 outlines that the congregation must offer a young bullock for a burnt offering and a kid for a sin offering when sin is committed in ignorance. This sacrificial system reveals God's provision for corporate atonement (Leviticus 4:13-21, Hebrews 9:7).",
          "verseReference": "Numbers 15:24",
          "difficulty": "hard"
        },
        {
          "id": "numbers-15-theological-q5",
          "question": "What is the consequence for one who sins presumptuously, despising the LORD's commandment?",
          "type": "multiple-choice",
          "options": [
            "That soul shall be cut off from among his people",
            "He shall be forgiven after repentance",
            "He shall bring a sin offering",
            "He shall be publicly rebuked"
          ],
          "correctAnswer": "That soul shall be cut off from among his people",
          "explanation": "Numbers 15:30-31 states that one who sins presumptuously and despises God's word shall be cut off. This shows God's holiness and justice in dealing with willful rebellion (Deuteronomy 17:12, Ezekiel 18:24, Hebrews 10:26-27).",
          "verseReference": "Numbers 15:30",
          "difficulty": "hard"
        },
        {
          "id": "numbers-15-theological-q6",
          "question": "What was the punishment for the man found gathering sticks on the Sabbath day?",
          "type": "multiple-choice",
          "options": [
            "He was stoned to death by all the congregation",
            "He was fined",
            "He was given a warning",
            "He was imprisoned for a day"
          ],
          "correctAnswer": "He was stoned to death by all the congregation",
          "explanation": "Numbers 15:35-36 records that the man gathering sticks on the Sabbath was stoned to death. This exemplifies the seriousness of Sabbath observance as a covenant sign (Exodus 31:14, Ezekiel 20:12, Hebrews 4:9-10).",
          "verseReference": "Numbers 15:35",
          "difficulty": "hard"
        },
        {
          "id": "numbers-15-theological-q7",
          "question": "What is the significance of the fringes on the borders of garments with a blue ribbon as commanded in Numbers 15?",
          "type": "multiple-choice",
          "options": [
            "To remind Israelites to keep all commandments and be holy",
            "To identify the priests only",
            "To show social status",
            "To decorate the garments"
          ],
          "correctAnswer": "To remind Israelites to keep all commandments and be holy",
          "explanation": "Numbers 15:38-40 explains the fringes with a blue ribbon serve as a visual reminder to obey God's commandments and live holy lives. This practice symbolizes covenant faithfulness (Deuteronomy 22:12, Matthew 23:5, Revelation 15:6).",
          "verseReference": "Numbers 15:38",
          "difficulty": "hard"
        },
        {
          "id": "numbers-15-theological-q8",
          "question": "What is the prescribed drink offering quantity for a ram burnt offering?",
          "type": "multiple-choice",
          "options": [
            "The third part of an hin of wine",
            "Half an hin of wine",
            "A fourth part of an hin of wine",
            "One hin of wine"
          ],
          "correctAnswer": "The third part of an hin of wine",
          "explanation": "Numbers 15:7 details that the drink offering for a ram is a third part of an hin of wine. This precise measurement illustrates God’s detailed instructions for worship (Leviticus 23:13, Exodus 29:40).",
          "verseReference": "Numbers 15:7",
          "difficulty": "hard"
        },
        {
          "id": "numbers-15-theological-q9",
          "question": "What must be offered as a heave offering when the Israelites eat the bread of the land?",
          "type": "multiple-choice",
          "options": [
            "A cake of the first of your dough",
            "A lamb without blemish",
            "A kid of the goats",
            "A burnt bullock"
          ],
          "correctAnswer": "A cake of the first of your dough",
          "explanation": "Numbers 15:19-20 instructs that when eating bread from the land, a cake of the first dough is offered as a heave offering. This acknowledges God's provision and sanctifies their sustenance (Exodus 23:19, Deuteronomy 26:1-4, Romans 11:16).",
          "verseReference": "Numbers 15:19",
          "difficulty": "hard"
        },
        {
          "id": "numbers-15-theological-q10",
          "question": "What does Numbers 15 teach about God's character in relation to ignorance and sin?",
          "type": "multiple-choice",
          "options": [
            "God provides a way to atone for sins committed in ignorance",
            "God ignores sins committed in ignorance",
            "God punishes all sins equally without distinction",
            "God only forgives intentional sins"
          ],
          "correctAnswer": "God provides a way to atone for sins committed in ignorance",
          "explanation": "Numbers 15:22-29 explains that for sins committed in ignorance, there are specific offerings and atonement. This reveals God's mercy and justice (Leviticus 4:2-35, Psalm 103:12, Hebrews 9:7).",
          "verseReference": "Numbers 15:22",
          "difficulty": "hard"
        },
        {
          "id": "numbers-15-theological-q11",
          "question": "Who must bring offerings by fire when they come into the land according to Numbers 15?",
          "type": "multiple-choice",
          "options": [
            "All born in the country and strangers dwelling among them",
            "Only the priests",
            "Only the native-born Israelites",
            "Only the elders"
          ],
          "correctAnswer": "All born in the country and strangers dwelling among them",
          "explanation": "Numbers 15:13-15 mandates that both native-born Israelites and strangers must bring offerings by fire alike. This shows God's inclusive covenant community and uniform standards (Exodus 12:49, Leviticus 24:22, Galatians 3:28).",
          "verseReference": "Numbers 15:13",
          "difficulty": "hard"
        },
        {
          "id": "numbers-15-theological-q12",
          "question": "What is the theological significance of the detailed measurements for offerings in Numbers 15?",
          "type": "multiple-choice",
          "options": [
            "They reflect God's holiness and the need for precise obedience",
            "They are arbitrary and symbolic only",
            "They were meant for convenience",
            "They represent human traditions"
          ],
          "correctAnswer": "They reflect God's holiness and the need for precise obedience",
          "explanation": "The detailed offerings (Numbers 15:4-10) demonstrate God's demand for holiness and exactness in worship, paralleling Leviticus 10:1-7 and Hebrews 12:14 which emphasize holiness and reverence.",
          "verseReference": "Numbers 15:4",
          "difficulty": "hard"
        },
        {
          "id": "numbers-15-theological-q13",
          "question": "What does the punishment for Sabbath violation in Numbers 15 reveal about God's covenant?",
          "type": "multiple-choice",
          "options": [
            "God's covenant includes serious obligations that reflect His holiness",
            "The Sabbath is optional",
            "God tolerates Sabbath violations",
            "Sabbath laws were only cultural, not divine"
          ],
          "correctAnswer": "God's covenant includes serious obligations that reflect His holiness",
          "explanation": "The execution of the man gathering sticks on Sabbath (Numbers 15:32-36) highlights the seriousness of covenant obedience and God's holiness (Exodus 31:13, Ezekiel 20:12, Hebrews 4:1-11).",
          "verseReference": "Numbers 15:32",
          "difficulty": "hard"
        },
        {
          "id": "numbers-15-theological-q14",
          "question": "How does Numbers 15:41 identify God in relation to Israel’s history and identity?",
          "type": "multiple-choice",
          "options": [
            "The LORD your God who brought you out of Egypt to be your God",
            "A distant god uninvolved in history",
            "A god of agriculture and seasons",
            "A god who accepts all religions"
          ],
          "correctAnswer": "The LORD your God who brought you out of Egypt to be your God",
          "explanation": "Numbers 15:41 affirms God's covenant faithfulness as the deliverer from Egypt and personal God to Israel, consistent with Exodus 6:7 and Deuteronomy 7:9, emphasizing God's saving and covenantal nature.",
          "verseReference": "Numbers 15:41",
          "difficulty": "hard"
        },
        {
          "id": "numbers-15-theological-q15",
          "question": "What theological theme is emphasized by the requirement that strangers follow the same ordinances as the Israelites?",
          "type": "multiple-choice",
          "options": [
            "God’s covenantal inclusion and justice apply universally",
            "Strangers are excluded from salvation",
            "Only Israelites can worship rightly",
            "Strangers can ignore God's commands"
          ],
          "correctAnswer": "God’s covenantal inclusion and justice apply universally",
          "explanation": "Numbers 15:14-16 shows that strangers are bound by the same laws, revealing God's justice and inclusive plan for all peoples (Leviticus 19:33-34, Galatians 3:28, Ephesians 2:19).",
          "verseReference": "Numbers 15:14",
          "difficulty": "hard"
        }
      ],
      "difficulty": "hard",
      "isBookQuiz": false,
      "slug": "numbers-15-quiz",
      "tags": [
        "numbers",
        "chapter-15",
        "numbers",
        "bible-quiz",
        "theological"
      ],
      "totalQuestions": 15,
      "estimatedTime": 25
    }
  }
}