{
  "1": {
    "title": "Encouragement to Timothy",
    "keyEvent": "Paul urges Timothy to be strong in faith",
    "verses": 18
  },
  "2": {
    "title": "Faithful Ministry Instructions",
    "keyEvent": "Paul instructs Timothy on faithful teaching and endurance",
    "verses": 26
  },
  "3": {
    "title": "Warnings and Godliness",
    "keyEvent": "Paul warns of perilous times and describes godly conduct",
    "verses": 17
  },
  "4": {
    "title": "Final Charge and Farewell",
    "keyEvent": "Paul charges Timothy to preach and shares personal farewell",
    "verses": 22
  }
}